[{"name":"SALAD","clues":[{"clue":"How about one of these Mexican salads? Its name means \"toasted\\\"","response":"tostada","value":200,"isDailyDouble":false},{"clue":"This salad of tomatoes & mozzarella gets its name from an island near the Bay of Naples","response":"caprese","value":400,"isDailyDouble":false},{"clue":"Add some crunch to your salad with this white-fleshed veggie also called a Mexican potato","response":"jicama","value":600,"isDailyDouble":false},{"clue":"This salad with chopped turkey, bacon, tomatoes & hard-boiled eggs is named for the owner of the Brown Derby","response":"a Cobb salad","value":800,"isDailyDouble":false},{"clue":"This \"colorful\" salad dressing was created in San Francisco in the 1920s & named for a play","response":"Green Goddess","value":1000,"isDailyDouble":false}]},{"name":"NURSERY RHYMES","clues":[{"clue":"Since she had a bare cupboard, hers certainly wasn't a lucky dog, lucky dog","response":"Old Mother Hubbard","value":200,"isDailyDouble":false},{"clue":"Precarious position of the bough-borne cradle","response":"up in the treetop","value":400,"isDailyDouble":false},{"clue":"\\\"See-saw, Margery Daw,\" he \"shall have a new master\\\"","response":"Jacky","value":600,"isDailyDouble":false},{"clue":"A 2nd verse to this rhyme begins \"Every fiddler he had a fiddle, and a very fine fiddle had he\\\"","response":"\\\"Old King Cole\\\"","value":800,"isDailyDouble":false},{"clue":"In this rhyme, a parent bemoans the fact her child has gone to bed with stockings & 1 shoe on","response":"\\\"Diddle Diddle Dumpling\\\"","value":1000,"isDailyDouble":false}]},{"name":"BRITISH ENGLISH","clues":[{"clue":"A large bus for traveling in the U.K.; in the U.S. it's a person who guides a sports team","response":"a coach","value":200,"isDailyDouble":false},{"clue":"The Brits put their trousers on one leg at a time; this 5-letter word that Americans use means underwear over there","response":"pants","value":400,"isDailyDouble":false},{"clue":"A dummy in Devon is this accessory for a baby","response":"a pacifier","value":600,"isDailyDouble":false},{"clue":"In the U.K., chemist means someone in this profession","response":"pharmacist","value":800,"isDailyDouble":false},{"clue":"If you ask for chips in England, you'll get French fries; if you want potato chips, ask for these","response":"crisps","value":1000,"isDailyDouble":false}]},{"name":"IT'S \"OVER\\\"","clues":[{"clue":"In both the Old & New Testaments, it's referred to as \"The Feast of Unleavened Bread\\\"","response":"Passover","value":200,"isDailyDouble":false},{"clue":"By definition hyperthyroidism is a condition in which the thyroid is this","response":"overactive","value":400,"isDailyDouble":false},{"clue":"This hairstyle used to cover up a bald spot often just draws more attention to it","response":"a comb over","value":600,"isDailyDouble":false},{"clue":"Nearly cut from the film, this classic ballad won the Oscar for best song of 1939","response":"\\\"Over The Rainbow\\\"","value":800,"isDailyDouble":false},{"clue":"The Allied invasion that began June 6, 1944 was codenamed Operation this","response":"Overlord","value":1000,"isDailyDouble":false}]},{"name":"THE CIRCUS","clues":[{"clue":"Legend says Isaac van Amburgh was the first to stick his head here—we hope he got a \"roar\" of applause","response":"a lion's mouth","value":200,"isDailyDouble":false},{"clue":"King Tusk, a famous one of these animals, outweighs Jumbo by more than 1,000 pounds","response":"an elephant","value":400,"isDailyDouble":false},{"clue":"Baraboo, Wisc.'s Circus World Museum is on the grounds of the original winter home of these brothers' circus","response":"the Ringling Brothers","value":600,"isDailyDouble":false},{"clue":"Red Skelton's father, who died before Red was born, was one of these circus performers","response":"a clown","value":800,"isDailyDouble":false},{"clue":"In 1982 Miguel Vazquez became the 1st aerialist to accomplish a quadruple one of these in performance","response":"somersault","value":1000,"isDailyDouble":false}]},{"name":"AMERICAN HISTORY","clues":[{"clue":"This state's been \"on my mind\" since it entered the Union 3 times, in 1788, 1868 & 1870","response":"Georgia","value":200,"isDailyDouble":false},{"clue":"In 1913 the 16th Amendment was passed allowing Congress to collect taxes on this","response":"income","value":400,"isDailyDouble":false},{"clue":"Fleeing the capital on August 24, 1814, she took a Gilbert Stuart portrait of Washington with her","response":"Dolley Madison","value":600,"isDailyDouble":false},{"clue":"Guerrilla leader Francis Marion earned this nickname for his daring raids from the South Carolina marshes","response":"the Swamp Fox","value":800,"isDailyDouble":false},{"clue":"Name that completed an 1856 Republican slogan, \"Free soil, free speech, free men and...\\\"","response":"Fremont","value":1000,"isDailyDouble":true}]},{"name":"FOOD STUFF","clues":[{"clue":"One of Cracker Barrel's fancy fixin's is country fried (not chicken fried) this","response":"steak","value":200,"isDailyDouble":false},{"clue":"You don't need your oven to make this appetizer—a lime juice marinade does the cooking","response":"ceviche","value":400,"isDailyDouble":false},{"clue":"On this 5-letter diet, you eat like our ancient ancestors—more nuts, less wheat","response":"the paleo diet","value":600,"isDailyDouble":false},{"clue":"In the cuisine of this country of more than 100 million, injera is the bread & the dipping spoon all in one","response":"Ethiopia","value":800,"isDailyDouble":false},{"clue":"The morel is Minnesota's state one of these","response":"a mushroom","value":1000,"isDailyDouble":false}]},{"name":"THAT'S AWFUL GRIMM","clues":[{"clue":"These 2 kids, near-victims of cannibalization, burn a woman to death & don't think twice about it","response":"Hansel & Gretel","value":200,"isDailyDouble":false},{"clue":"The final words in \"The Death of the Little\" this, a female domestic fowl— \"and then everyone was dead\\\"","response":"the hen","value":400,"isDailyDouble":false},{"clue":"When 2 girls get too rough playing with a bear, the bear says, this girl & \"Rose-Red, will you beat your wooer dead?\\\"","response":"Snow White","value":600,"isDailyDouble":false},{"clue":"\\\"The Twelve Brothers\" ends with this \"wicked\" relative \"put into a barrel filled with boiling oil and venomous snakes\\\"","response":"the stepmother","value":800,"isDailyDouble":false},{"clue":"In this tale a woman cuts off her own toe to fit into some footwear","response":"\\\"Cinderella\\\"","value":1000,"isDailyDouble":false}]},{"name":"RIPPED FROM THE HEADLINES","clues":[{"clue":"These animals \"Lose Their Jobs as Milk Prices Drop\\\"","response":"cows","value":200,"isDailyDouble":false},{"clue":"\\\"Marijuana Issue Sent to\" this \"Committee\", generally composed of members of both houses of a legislature","response":"joint committee","value":400,"isDailyDouble":false},{"clue":"Hips don't lie, nor does this singer, who \"says 'People Were Just Watching' & didn't help when wild boars robbed her in Barcelona\\\"","response":"Shakira","value":600,"isDailyDouble":false},{"clue":"\\\"California\" these birds \"Are Very Rare, But 10% of Them Are Trashing\" a house in Tehachapi","response":"condors","value":800,"isDailyDouble":false},{"clue":"\\\"Thanks to a Glitch, Some Seattle Mazda Drivers Can't Tune Their Radios Away From\" NPR, so at 7 A.M., it's this show or nothing","response":"Morning Edition","value":1000,"isDailyDouble":false}]},{"name":"IT'S ALL A BUNCH OF LIES","clues":[{"clue":"Although written by Parson Weems, the line \"I can't tell a lie. I did cut it with my hatchet\" is often attributed to him","response":"George Washington","value":200,"isDailyDouble":false},{"clue":"This \"hot\" hit by The Doors begins, \"You know that it would be untrue, you know that I would be a liar...\\\"","response":"\\\"Light My Fire\\\"","value":400,"isDailyDouble":false},{"clue":"In 1925 he wrote, \"The great masses of the people...will more easily fall victim to a big lie than to a small one\\\"","response":"Adolf Hitler","value":600,"isDailyDouble":false},{"clue":"In \"Pudd'nhead Wilson\" he wrote, \"One of the differences between a cat & a lie is that a cat has only 9 lives\\\"","response":"Mark Twain","value":800,"isDailyDouble":false},{"clue":"This early 20th century humorist quipped, \"Income tax has made liars out of more Americans than golf\\\"","response":"Will Rogers","value":1000,"isDailyDouble":false}]},{"name":"SOUTH DAKOTA","clues":[{"clue":"Tho in real life he was between McKinley & Taft, on Mt. Rushmore he's between Jefferson & Lincoln","response":"Teddy Roosevelt","value":200,"isDailyDouble":false},{"clue":"The dark ponderosa pines gave this famous region its name","response":"Black Hills","value":400,"isDailyDouble":false},{"clue":"In Deadwood, one can visit the grave sites of this legendary wild west \"couple\\\"","response":"Calamity Jane & Wild Bill Hickok","value":600,"isDailyDouble":false},{"clue":"1 of the 2 national parks in South Dakota","response":"Badlands (Wind Cave)","value":800,"isDailyDouble":false},{"clue":"It's approximately 17 miles west of Castle Rock, South Dakota, at about 104° w. longitude, 45° n. latitude","response":"geographical center of the U.S.A.","value":1000,"isDailyDouble":false}]},{"name":"SUPER TOUGH ANAGRAMS","clues":[{"clue":"On the \"Oklahoma!\" soundtrack, you'll hear \"I'm Jist A Girl Who Cain't Say\" this","response":"No (on)","value":200,"isDailyDouble":false},{"clue":"For Al Hirt it's a note to follow so","response":"la (Al)","value":400,"isDailyDouble":false},{"clue":"An ad for a Russian perfume might read, \"Her lips said nyet, but her perfume said\" this","response":"da (ad)","value":600,"isDailyDouble":false},{"clue":"For me this measure for 12-point type is just fine","response":"em (me)","value":800,"isDailyDouble":false},{"clue":"It is a tropical shrub","response":"ti (it)","value":1000,"isDailyDouble":false}]},{"name":"RELIGION","clues":[{"clue":"The Christ child replaced St. Nicholas as the bringer of gifts as part of this movement led by Martin Luther","response":"Reformation","value":200,"isDailyDouble":false},{"clue":"Mahayana & Theravada are 2 divisions of this Eastern religion","response":"Buddhism","value":400,"isDailyDouble":false},{"clue":"The Umrah pilgrimage to Mecca can happen almost any time of the year, unlike this one that must happen in the month of Dhu al-Hijjah","response":"the Hajj","value":600,"isDailyDouble":true},{"clue":"(Sarah of the Clue Crew presents from the Great Synagogue in Budapest, Hungary.) The largest in Europe, the Great Synagogue of Budapest can seat 3,000 people; traditionally, the men sit downstairs while the women are in the balcony, a universal practice in this branch of Judaism","response":"Orthodox","value":800,"isDailyDouble":false},{"clue":"The Beachy church of this American group allows automobiles but no TV","response":"Amish","value":1000,"isDailyDouble":false}]},{"name":"WORD ORIGINS","clues":[{"clue":"A poem composed as a lament for the dead, its name comes from elegos, \"mournful song\\\"","response":"elegy","value":200,"isDailyDouble":false},{"clue":"A keepsake, its name comes from meminisse, \"to remember\\\"","response":"memento","value":400,"isDailyDouble":false},{"clue":"The name of this blue dye flows back to the Indus River","response":"indigo","value":600,"isDailyDouble":false},{"clue":"This dance's name is derived from Polish meaning \"from the province of Mazovia\\\"","response":"mazurka","value":800,"isDailyDouble":false},{"clue":"The name of this flowering plant may come from a name of the god Apollo, Paion","response":"the peony","value":1000,"isDailyDouble":false}]},{"name":"TELEVISION ODDITIES","clues":[{"clue":"Bush asked him, \"How'd you like it if I judged your career by those 7 minutes when you walked off the set?\\\"","response":"Dan Rather","value":200,"isDailyDouble":false},{"clue":"In L.A. on both Feb. 4 & 5, 1988, the 8:00 movie on 3 TV stations starred this man; talk about a death wish!","response":"Charles Bronson","value":400,"isDailyDouble":false},{"clue":"Kraft is using the song \"New York, New York\" in commercials for this brand of cream cheese","response":"Philadelphia brand cream cheese","value":600,"isDailyDouble":false},{"clue":"Todd Waring took over this actor's roles in the TV versions of both \"Nothing in Common\" & \"Splash\\\"","response":"Tom Hanks","value":800,"isDailyDouble":false},{"clue":"The title of this show stayed the same in 1982 even though half the title team left the show","response":"Laverne & Shirley","value":1000,"isDailyDouble":false}]},{"name":"ROAD SONGS","clues":[{"clue":"John Denver wanted these roads to \"take me home\\\"","response":"country roads","value":200,"isDailyDouble":false},{"clue":"It precedes \"and don't you come back no more, no more, no more, no more\\\"","response":"Hit the road Jack","value":400,"isDailyDouble":false},{"clue":"In question posed by The Beatles, \"Why don't we do\" this \"in the road?\\\"","response":"it","value":600,"isDailyDouble":false},{"clue":"If I take this, \"I'll be in Scotland before ye\\\"","response":"the low road","value":800,"isDailyDouble":false},{"clue":"1853 version of this begins \"Up & down the city road, in & out the eagle\\\"","response":"\\\"Pop Goes The Weasel\\\"","value":1000,"isDailyDouble":false}]},{"name":"CURRENT EVENTS","clues":[{"clue":"(Sarah of the Clue Crew delivers the clue from Alaska.) Flotsam ranging from small toys to a 200-foot squid trawler began washing up on Alaska's shores months after this March 2011 event","response":"the Japanese earthquake (or tsunami)","value":200,"isDailyDouble":false},{"clue":"A carcass that washed ashore in New Zealand in 2013 resembling some prehistoric sea monster was this, aka a killer whale","response":"an orca","value":400,"isDailyDouble":false},{"clue":"This Norwegian explorer was carried across the Atlantic by ocean currents in his reed boat Ra II","response":"Thor Heyerdahl","value":600,"isDailyDouble":false},{"clue":"In 2012 a Scottish skipper found one of these, also a song by the Police; it had been adrift for 97 years & 309 days","response":"a message in a bottle","value":800,"isDailyDouble":true},{"clue":"In 1835 this French engineer described the effect named for him, which influences the direction of ocean currents","response":"Coriolis","value":1000,"isDailyDouble":false}]},{"name":"HODGEPODGE","clues":[{"clue":"Animal Planet is on its 11th version of this annual feature with a different feel from the big football game","response":"the Puppy Bowl","value":200,"isDailyDouble":false},{"clue":"This cold soup is a puree of tomatoes & green peppers; in its homeland of Spain, cookbooks classify it as salad","response":"gazpacho","value":400,"isDailyDouble":false},{"clue":"The American Bar Association's ethical rules include protection of confidences under attorney-client this","response":"privilege","value":600,"isDailyDouble":false},{"clue":"This consortium of colleges traces its origins to a conference held at Vassar College in 1915","response":"the Seven Sisters","value":800,"isDailyDouble":false},{"clue":"In 1798 Congress passed these 4 internal security laws aimed at immigrants & at curtailing the press","response":"the Alien and Sedition Acts","value":1000,"isDailyDouble":false}]},{"name":"19th CENTURY NOVELS","clues":[{"clue":"Huckleberry Finn is introduced, carrying a dead cat, in chapter 6 of this novel","response":"Tom Sawyer","value":200,"isDailyDouble":false},{"clue":"The brooding Dmitri is the oldest of the title characters in this 1879 work","response":"The Brothers Karamazov","value":400,"isDailyDouble":false},{"clue":"Character who (ironically) remarks, \"I shall grow old, and horrible... but this picture will remain always young\\\"","response":"Dorian Gray","value":600,"isDailyDouble":false},{"clue":"He wasn't at ease writing 1896's \"An Outcast of the lslands\" in English, but by \"Lord Jim\", he had the knack","response":"Joseph Conrad","value":800,"isDailyDouble":false},{"clue":"Stendhal's \"The Charterhouse of\" this place is set in a prince's court in northern Italy","response":"Parma","value":1000,"isDailyDouble":false}]},{"name":"THE \"IN\" SOUND","clues":[{"clue":"The South American empire of these people included parts of present-day Ecuador, Peru, Chile & Argentina","response":"Incas","value":200,"isDailyDouble":false},{"clue":"From the Latin for \"to set on fire\", it's an aromatic substance burned to produce a pleasant odor","response":"incense","value":400,"isDailyDouble":false},{"clue":"The main islands of this country include Borneo, Sulawesi, Java & Sumatra","response":"Indonesia","value":600,"isDailyDouble":false},{"clue":"Usually the largest branch of an army, it's another name for foot soldiers","response":"infantry","value":800,"isDailyDouble":false},{"clue":"A furnace-like device for reducing waste products to ash","response":"incinerator","value":1000,"isDailyDouble":false}]},{"name":"COLLEGE FOOTBALL 2000","clues":[{"clue":"In 2000 this conference had 3 teams win 10 or more games: Washington, Oregon & Oregon state","response":"the Pac-10","value":200,"isDailyDouble":false},{"clue":"This school's Huskers set a college bowl record by scoring 66 points against Northwestern in the Alamo Bowl","response":"the University of Nebraska","value":400,"isDailyDouble":false},{"clue":"The USA's only major undefeated team, it won the national title by beating Florida State in the Orange Bowl","response":"Oklahoma","value":600,"isDailyDouble":false},{"clue":"Lou Holtz coached this school's Gamecocks to an 8-4 record after a winless season in 1999","response":"South Carolina","value":800,"isDailyDouble":false},{"clue":"A sprained ankle forced this Virginia Tech QB (& Heisman hopeful) to miss 1 game & parts of 2 others during 2000","response":"Michael Vick","value":1000,"isDailyDouble":false}]},{"name":"AMERICAN PRODUCTS ABROAD","clues":[{"clue":"In 1984 this chain sold its 50 billionth hamburger & opened in Finland & Taiwan","response":"McDonald's","value":200,"isDailyDouble":false},{"clue":"Oxford House in Hong Kong clocks in as the home of the Asia edition of this newsmagazine","response":"Time","value":400,"isDailyDouble":false},{"clue":"Can't keep this co. bottled up—it was the first U.S. co. to distribute in China when that nation was opened in 1979","response":"Coke","value":600,"isDailyDouble":false},{"clue":"In 1889 the Eastman Company was incorporated in London to distribute products under this snappy name","response":"Kodak","value":800,"isDailyDouble":false},{"clue":"(Sarah of the Clue Crew reports from a marketplace in Moscow, Russia.) This 150-year-old San Francisco brand used to be a coveted black market item here in Russia; now it's commonplace","response":"Levi Strauss","value":1000,"isDailyDouble":false}]},{"name":"COMMUNITY COLLEGES","clues":[{"clue":"The Kapi'olani Community College is part of the university of this state","response":"Hawaii","value":200,"isDailyDouble":false},{"clue":"You either graduate from this community college in Colorado Springs, or you bust","response":"Pikes Peak Community College","value":400,"isDailyDouble":false},{"clue":"Manatee Community College is in Bradenton in this state","response":"Florida","value":600,"isDailyDouble":false},{"clue":"Don't want to end up parking cars? Try Henry Ford Community College in this Michigan city","response":"Dearborn","value":800,"isDailyDouble":false},{"clue":"Cape Cod Community College is in Massachusetts; Cape Fear Community College is in this state","response":"North Carolina","value":1000,"isDailyDouble":false}]},{"name":"AMERICAN CITIES","clues":[{"clue":"\\\"Earthquake City\" & \"Baghdad by the Bay\" are 2 nicknames of this California city","response":"San Francisco","value":200,"isDailyDouble":false},{"clue":"The U.S.A.F. Academy is located outside this Colorado city home to the main U.S. Olympic Training Center","response":"Colorado Springs","value":400,"isDailyDouble":false},{"clue":"Many visitors to the Big Apple fly into this city's Liberty Airport, maybe on Continental","response":"Newark","value":600,"isDailyDouble":false},{"clue":"\\\"Cross and Sword\", Florida's official state play, was created to reenact this city's founding in 1565","response":"St. Augustine","value":800,"isDailyDouble":true},{"clue":"In 1882 the Knights of Columbus was founded in this \"new\" Connecticut city","response":"New Haven","value":1000,"isDailyDouble":false}]},{"name":"TV COPS","clues":[{"clue":"Perhaps the only cop who ever asked a crook \"Who loves ya, baby?\\\"","response":"Kojak","value":200,"isDailyDouble":false},{"clue":"Its lead character introduced himself with, \"My name's Friday; I'm a cop\\\"","response":"Dragnet","value":400,"isDailyDouble":false},{"clue":"Series William Shatner has starred in since he came down to Earth","response":"T.J. Hooker","value":600,"isDailyDouble":false},{"clue":"Comic question asked of officers Toody & Muldoon","response":"Car 54, Where Are You?","value":800,"isDailyDouble":false},{"clue":"This show only gained popularity in re-release after Burt Reynolds became a star","response":"Dan August","value":1000,"isDailyDouble":false}]},{"name":"VISITING ATLANTA","clues":[{"clue":"His crypt, in a reflecting pool, is engraved, \"Free at last, free at last, thank God almighty, I'm free at last\\\"","response":"Dr. Martin Luther King Jr.","value":200,"isDailyDouble":false},{"clue":"Maybe you'll crack the secret recipe when you visit the \"World of\" this soft drink","response":"Coca-Cola","value":400,"isDailyDouble":false},{"clue":"The Cobb Energy Performing Arts Centre stood in on this TV show as the CDC, which didn't solve the zombie problem","response":"The Walking Dead","value":600,"isDailyDouble":false},{"clue":"A VIP tour of its headquarters includes a visit to the HLN control room","response":"CNN","value":800,"isDailyDouble":false},{"clue":"The Michael C. Carlos Museum is on the campus of this university named for a bishop","response":"Emory","value":1000,"isDailyDouble":false}]},{"name":"POTENT POTABLES","clues":[{"clue":"On a cold wintry night, warm up with a traditional hot buttered this drink","response":"rum","value":200,"isDailyDouble":false},{"clue":"Ilchester is a cheese created in 1962 by adding this potent potable to Cheddar","response":"beer","value":400,"isDailyDouble":false},{"clue":"Gusano Rojo is a popular brand of this tequila relative known for sometimes having a worm in the bottle","response":"mescal","value":600,"isDailyDouble":false},{"clue":"This type of booze is also a letter in the NATO phonetic alphabet","response":"whiskey","value":800,"isDailyDouble":false},{"clue":"This yellow-green liqueur is made by Carthusian monks","response":"Chartreuse","value":1000,"isDailyDouble":false}]},{"name":"BATTLE TO NAME THE WAR","clues":[{"clue":"The Battle of Stalingrad","response":"World War II","value":200,"isDailyDouble":false},{"clue":"Quang Tri City; the cavalry was sent!","response":"the Vietnam War","value":400,"isDailyDouble":false},{"clue":"Quebec &, a year later, Trenton","response":"the Revolutionary War","value":600,"isDailyDouble":false},{"clue":"No one enjoyed the portions at Pork Chop Hill","response":"the Korean War","value":800,"isDailyDouble":false},{"clue":"Let me take you down, 'cause we're going to... Bosworth Field","response":"the War of the Roses","value":1000,"isDailyDouble":false}]},{"name":"CANADIAN HISTORY","clues":[{"clue":"The 1842 Webster-Ashburton Treaty fixed Maine's border with this \"New\" province","response":"New Brunswick","value":200,"isDailyDouble":false},{"clue":"This military alliance was formed in 1949 by Canada, the U.S. & 10 European countries","response":"NATO (North Atlantic Treaty Organization)","value":400,"isDailyDouble":false},{"clue":"On a tour of Canada in 1967, French president Charles de Gaulle called for the independence of this province","response":"Quebec","value":600,"isDailyDouble":false},{"clue":"This institution, the NFB, founded by Parliament in 1939, added an animation department in 1942","response":"National Film Board of Canada","value":800,"isDailyDouble":false},{"clue":"This Canadian company, formerly British, is the oldest chartered company in the world","response":"Hudson's Bay Company","value":1000,"isDailyDouble":false}]},{"name":"PLUMBING","clues":[{"clue":"When you do this, the stopper ball lifts to allow water from the tank to flow into the bowl","response":"Flush the toilet","value":200,"isDailyDouble":false},{"clue":"Doing this to a pipe, unlike doing it to a needle, involves special cutting tools","response":"Threading","value":400,"isDailyDouble":false},{"clue":"You may run your dishwasher's drain line under the sink into this other labor-saving device","response":"Garbage disposal","value":600,"isDailyDouble":false},{"clue":"This rhyming device sucks up water to prevent basement flooding","response":"Sump pump","value":800,"isDailyDouble":false},{"clue":"This L-shaped \"hex\" wrench was named for a Hartford, Connecticut manufacturer","response":"Allen wrench","value":1000,"isDailyDouble":false}]},{"name":"TRANSPORTATION","clues":[{"clue":"A 1984 count reportedly indicated this city's streets contained 927,000 potholes","response":"New York City","value":200,"isDailyDouble":false},{"clue":"While in office, he became 1st president to ride in a car & submerge in a submarine","response":"Theodore Roosevelt","value":400,"isDailyDouble":false},{"clue":"Guiness says on a calm night in 1966 one of these became largest object ever stolen by one man","response":"a freighter (ship)","value":600,"isDailyDouble":false},{"clue":"Group which topped the country charts with the following song about a truck driver: [Truck noises] \"Roll on, highway / Roll on along / Roll on, Daddy, 'til you get back home / Roll on family / Roll on crew / Roll on, Mama, like I asked you to do / And roll on eighteen wheeler, roll on / (Roll on!)...\\\"","response":"Alabama","value":800,"isDailyDouble":true},{"clue":"In production from 1897 to 1924, this car was nicknamed \"The Tea Kettle\\\"","response":"the Stanley Steamer","value":1000,"isDailyDouble":false}]},{"name":"COURSES AT CALTECH","clues":[{"clue":"\\\"Human\" this process covers natural selection & genetics","response":"evolution","value":200,"isDailyDouble":false},{"clue":"4 letters preceding \"technology\" in a course that explores \"miniaturization of devices to the smallest scale\\\"","response":"nano","value":400,"isDailyDouble":false},{"clue":"The techies take a humanities break in \"From Van Eyck to\" this master painter of the Dutch golden age","response":"Rembrandt","value":600,"isDailyDouble":false},{"clue":"\\\"Engineering\" this -ology examines earthquakes from the engineering perspective","response":"seismology","value":800,"isDailyDouble":false},{"clue":"Master the introduction \"to guidance, navigation, and control\" & you'll get an \"A\" in this \"engineering\\\"","response":"aerospace","value":1000,"isDailyDouble":false}]},{"name":"TOMMY ROT!","clues":[{"clue":"This inventor is buried on the grounds of Glenmont, his West Orange, New Jersey home","response":"Thomas Edison","value":200,"isDailyDouble":false},{"clue":"Oddly, his tombstone mentions nothing about him being president","response":"Thomas Jefferson","value":400,"isDailyDouble":false},{"clue":"This English portrait painter died in 1788 & was buried in Kew Churchyard","response":"Thomas Gainsborough","value":600,"isDailyDouble":false},{"clue":"Like Norse warriors, this trombonist & bandleader is in Valhalla — Valhalla, New York's Kensico Cemetery","response":"Tommy Dorsey","value":800,"isDailyDouble":false},{"clue":"In 1955 this novelist wasn't buried at \"Magic Mountain\" but in Kilchberg, near Zurich","response":"Thomas Mann","value":1000,"isDailyDouble":false}]},{"name":"\\\"HERB\"s","clues":[{"clue":"When nominated by the GOP for the presidency in 1928, he was serving as Secretary of Commerce","response":"Herbert Hoover","value":200,"isDailyDouble":false},{"clue":"He's been TV's \"Mr. Wizard\" since 1951","response":"Don Herbert","value":400,"isDailyDouble":false},{"clue":"There was a 9-year span between his first novel, \"The Dragon in the Sea\", & his second, \"Dune\\\"","response":"Frank Herbert","value":600,"isDailyDouble":false},{"clue":"In 1968 \"This Guy's In Love With You\" became his first No. 1 hit","response":"Herb Alpert","value":800,"isDailyDouble":false},{"clue":"This composer of \"Naughty Marietta\" has been called the \"prince of the operetta\\\"","response":"Victor Herbert","value":1000,"isDailyDouble":false}]},{"name":"CLASSICAL MUSIC","clues":[{"clue":"Way before Benny Goodman, the direction \"mit Schwung\", meaning this, appeared on Wagner's scores","response":"with swing","value":200,"isDailyDouble":false},{"clue":"\\\"The Swan\", labeled \"D' Anni 93\" & dated 1737, is believed to be the last violin he ever made","response":"Stradivarius","value":400,"isDailyDouble":false},{"clue":"An international piano competition named for this pianist is held about every 4 years in Ft. Worth, Texas","response":"Van Cliburn","value":600,"isDailyDouble":false},{"clue":"Nicolai Berezowsky & Francis Poulenc have composed works about this kiddy lit elephant","response":"Babar","value":800,"isDailyDouble":false},{"clue":"Saint-Saens work based on a Henri Cazalis poem that begins \"Zig et zig et zig, la mort en cadence\\\"","response":"\\\"Danse macabre\" (the dance of death)","value":1000,"isDailyDouble":false}]},{"name":"PROPER NAMES","clues":[{"clue":"Win an Academy Award & you'll go home with this golden guy","response":"an Oscar","value":200,"isDailyDouble":false},{"clue":"The name of this towerlike framework over an oil well comes from that of a 17th century hangman","response":"a derrick","value":400,"isDailyDouble":false},{"clue":"\\\"Rags To Riches\" crooner Bennett could tell you it means \"stylish\\\"","response":"tony","value":600,"isDailyDouble":false},{"clue":"Derived from Scottish Gaelic, it's a narrow, secluded valley, as Ms. Close might tell you","response":"a glen","value":800,"isDailyDouble":false},{"clue":"You might remember that this herb with needle-shaped leaves is a traditional seasoning for lamb","response":"rosemary","value":1000,"isDailyDouble":true}]},{"name":"SHAPELY SPEECH","clues":[{"clue":"Pay an airline for your flight there & back & you've bought this kind of ticket","response":"round trip","value":200,"isDailyDouble":false},{"clue":"An expansion of the West Wing in 1909 gave William Howard Taft this presidential room of power","response":"the Oval Office","value":400,"isDailyDouble":false},{"clue":"A nourishing repast is referred to in this \"boxy\" way","response":"a square meal","value":600,"isDailyDouble":false},{"clue":"This 3-dimensional figure \"of influence\" refers to the range of one nation's control over foreign territory","response":"a sphere","value":800,"isDailyDouble":false},{"clue":"Ranging from Myanmar to Laos to Thailand, Southeast Asia's major opium-producing region is called this","response":"the Golden Triangle","value":1000,"isDailyDouble":false}]},{"name":"SAY YES TO THE CHESS","clues":[{"clue":"In standard western chess sets, this piece is topped with a cross","response":"a king","value":200,"isDailyDouble":false},{"clue":"Chess games are typically divided into the opening, the middle game & this terminal phase","response":"the endgame","value":400,"isDailyDouble":false},{"clue":"It's the number of white squares on a standard chessboard","response":"32","value":600,"isDailyDouble":false},{"clue":"The queen's gambit is marked by white's second-move offer to sacrifice one of these, temporarily","response":"a pawn","value":800,"isDailyDouble":false},{"clue":"The \"hypermodern\" Reti opening begins with a move of this piece","response":"the white knight","value":1000,"isDailyDouble":false}]},{"name":"NURSERY RHYMES","clues":[{"clue":"When 1st told, it was Hjuki & Bil who carried the pail of water","response":"\\\"Jack and Jill\\\"","value":200,"isDailyDouble":false},{"clue":"About 1820, one reputedly followed Mary Sawyer to the Redstone School House in Massachusetts","response":"a little lamb","value":400,"isDailyDouble":false},{"clue":"At the Mad Tea Party, \"Twinkle, Twinkle, Little Star\" became \"Twinkle, Twinkle...\" this flying animal","response":"bat","value":600,"isDailyDouble":false},{"clue":"\\\"Diddle diddle, dumpling, my son John\" went to bed with one of these on","response":"shoe","value":800,"isDailyDouble":false},{"clue":"When the Queen of Hearts made her tarts","response":"on a summer's day","value":1000,"isDailyDouble":false}]},{"name":"HUMOROUS QUOTES","clues":[{"clue":"Oscar Wilde said, \"I like men who have a future and women who have\" this","response":"a past","value":200,"isDailyDouble":false},{"clue":"P.T. Barnum once punned, \"Every crowd has a silver\" one of these","response":"a lining","value":400,"isDailyDouble":false},{"clue":"Thomas A, Edision quipped, \"When down in the mouth, remember\" this biblical prophet, \"He came out all right.\\\"","response":"Jonah","value":600,"isDailyDouble":false},{"clue":"U.S. Grant said, \"I only know 2 tunes; one of them is\" this patriotic ditty \"and the other isn't.\\\"","response":"\\\"Yankee Doodle\\\"","value":800,"isDailyDouble":false},{"clue":"Paraphrasing Shakespeare, Dorothy Parker called it \"the soul of lingerie\\\"","response":"brevity","value":1000,"isDailyDouble":false}]},{"name":"\\\"G\"EOGRAPHY","clues":[{"clue":"This sacred river flows through Bangladesh before emptying into the Bay of Bengal","response":"Ganges","value":200,"isDailyDouble":false},{"clue":"2 rocks known as the Pillars of Hercules flank the eastern end of this strait","response":"Gibraltar","value":400,"isDailyDouble":false},{"clue":"Formerly occupied by Israel, this narrow piece of land reverted to Palestinian control in 1994","response":"Gaza Strip","value":600,"isDailyDouble":false},{"clue":"The name of this Asian desert is Mongolian for \"place without water\\\"","response":"Gobi","value":800,"isDailyDouble":false},{"clue":"Once known as the Enchanted Isles, they lie about 600 miles west of Ecuador","response":"Galapagos Islands","value":1000,"isDailyDouble":false}]},{"name":"ACTION CINEMA 2010!","clues":[{"clue":"Rampage was the name of an actor in this film; Faceman was the name of a character","response":"The A-Team","value":200,"isDailyDouble":false},{"clue":"This character took on \"the World\"—his new girlfriend's 7 evil ex-boyfriends, to be more specific","response":"(Scott) Pilgrim","value":400,"isDailyDouble":false},{"clue":"Nicolas Cage was magic as Balthazar, but as this film's title indicates, he needed a little help","response":"The Sorcerer's Apprentice","value":600,"isDailyDouble":false},{"clue":"One line sums up this film: \"Release the kraken!\" (we certainly saw it enough in the trailers!)","response":"Clash of the Titans","value":800,"isDailyDouble":false},{"clue":"Variety said this Sly Stallone pic had enough pyrotechnic displays to alter the planet's orbit","response":"The Expendables","value":1000,"isDailyDouble":false}]},{"name":"FRENCH MENU","clues":[{"clue":"I crave some sauce moutarde, named for this ingredient; I'll put in on everything","response":"mustard","value":200,"isDailyDouble":false},{"clue":"I want something rich: perhaps homard a la creme, this shellfish in a creamy sauce","response":"lobster","value":400,"isDailyDouble":false},{"clue":"Hmm... the name of these small cream puffs tells me that the restaurant makes quite a \"profit\" on them","response":"profiteroles","value":600,"isDailyDouble":false},{"clue":"Let's have oeufs a la Chartres, eggs flavored with this herb that the French call estragon","response":"tarragon","value":800,"isDailyDouble":false},{"clue":"Ah! A luscious gateau Montmorency, a cake topped with this fruit","response":"cherries","value":1000,"isDailyDouble":false}]},{"name":"LOVE CRAFT","clues":[{"clue":"As a tribute to your passion, create this type of work, a melange of different symbols meaningful to the beloved one","response":"a collage","value":200,"isDailyDouble":false},{"clue":"Want to make an anatomically correct felt heart for Valentine's Day? Make sure it has this many chambers","response":"4","value":400,"isDailyDouble":false},{"clue":"Susanna Hoffs loves this type of bracelet that sounds like the band she was in","response":"a bangle","value":600,"isDailyDouble":false},{"clue":"The do-it-yourself \"flowers\" imade from these paper breakfast helpers look great, but now I have none to hold my arabica","response":"coffee filters","value":800,"isDailyDouble":false},{"clue":"Be crafty & make your own one of these rings, given to a lover prior to an engagement ring","response":"a promise ring","value":1000,"isDailyDouble":false}]},{"name":"OCTOBER OBSERVANCES","clues":[{"clue":"The U.K. celebrates this fruit's day on October 21; events include the Longest Peel competition","response":"Apple Day","value":200,"isDailyDouble":false},{"clue":"In tribute to this man, the U.N. declared his birthday, October 2, International Day of Non-Violence","response":"(Mohandas) Gandhi","value":400,"isDailyDouble":false},{"clue":"Bring Fido & Felix to the Blessing of the Animals on October 4, the feast day of this saint","response":"St. Francis","value":600,"isDailyDouble":false},{"clue":"The invention of this language's alphabet by King Sejong on Oct. 8, 1446 is observed annually","response":"Korean","value":800,"isDailyDouble":false},{"clue":"October 10 is \"World\" this \"Health Day\", but it doesn't mean you're supposed to take one to skip work","response":"mental health","value":1000,"isDailyDouble":false}]},{"name":"COMIC STRIPPERS","clues":[{"clue":"Ruff, Mr. Wilson, Dennis Mitchell","response":"Dennis the Menace","value":200,"isDailyDouble":false},{"clue":"Jughead, Betty, Veronica Lodge","response":"Archie","value":400,"isDailyDouble":false},{"clue":"Aunt May, Dr. Doom, J. Jonah Jameson","response":"Spider-Man","value":600,"isDailyDouble":false},{"clue":"April O'Neil, Master Splinter, Donatello","response":"Teenage Mutant Ninja Turtles","value":800,"isDailyDouble":false},{"clue":"Elly, John, Michael, Elizabeth & April Patterson","response":"For Better or for Worse","value":1000,"isDailyDouble":false}]},{"name":"WORLD CITIES","clues":[{"clue":"George Square in this largest Scottish city has a very tall column with Sir Walter Scott atop it","response":"Glasgow","value":200,"isDailyDouble":false},{"clue":"It's the capital of the world's most populous country","response":"Beijing","value":400,"isDailyDouble":false},{"clue":"This capital of Australia's Northern Territory lies on Beagle Gulf","response":"Darwin","value":600,"isDailyDouble":true},{"clue":"(Vanna White delivers the clue from Jamaica.) Most cruise ships on Jamaica's northern coast dock at this port, whose name is Spanish for Eight Rivers","response":"Ocho Rios","value":800,"isDailyDouble":false},{"clue":"Once an imperial naval base, this Siberian port is headquarters to Russia's Pacific Fleet","response":"Vladivostok","value":1000,"isDailyDouble":false}]},{"name":"U.N. INTERNATIONAL YEARS","clues":[{"clue":"2019 is the Year of this array of elements, as it's the 150th anniversary","response":"the Periodic Table","value":200,"isDailyDouble":false},{"clue":"2009, the International Year of Astronomy, celebrated 400 years of this invention","response":"the telescope","value":400,"isDailyDouble":false},{"clue":"2013 was the Year of this staple Andean crop, which the U.N. hopes can help eradicate world hunger","response":"Quinoa","value":600,"isDailyDouble":true},{"clue":"2002 was the Year of this form of green travel, the visiting of natural habitats in a way that minimizes environmental impact","response":"Ecotourism","value":800,"isDailyDouble":false},{"clue":"1982 was the Year of Sanctions against this country that was suspended from the General Assembly in 1974 & readmitted in 1994","response":"South Africa","value":1000,"isDailyDouble":false}]},{"name":"PURSE-ONALITIES","clues":[{"clue":"Classic bag shapes inspire the Connecticut-based brand of purses called Dooney & this","response":"Bourke","value":200,"isDailyDouble":false},{"clue":"She was Kate Brosnahan when she designed her first utilitarian purses, sold now as this brand","response":"Kate Spade","value":400,"isDailyDouble":false},{"clue":"He's made his \"Marc\" with his luxury purses, which often feature his signature \"MJ\" push lock detail","response":"Marc Jacobs","value":600,"isDailyDouble":false},{"clue":"The \"LV\" monogram canvas of this brand dates to 1896","response":"Louis Vuitton","value":800,"isDailyDouble":false},{"clue":"The Birkin bag, named for actress Jane Birkin, is a status symbol from this French company","response":"Hermès","value":1000,"isDailyDouble":false}]},{"name":"INDEPENDENCE NATIONAL HISTORICAL PARK","clues":[{"clue":"(Kelly of the Clue Crew reports from Independence National Historical Park in Philadelphia, PA.) A quill box & shaker for sprinking sand over wet ink to speed drying are accessories of the silver ink stand used by the Declaration of Independence signers leading off with this Massachusetts man","response":"John Hancock","value":200,"isDailyDouble":false},{"clue":"(Kelly of the Clue Crew points to the post office at Independence National Historical Park in Philadelphia, PA.) The post office at 316 Market St. is the only one in the U.S. that doesn't fly the American flag, because it hadn't been created yet when this man was Postmaster-General","response":"Ben Franklin","value":400,"isDailyDouble":false},{"clue":"(Kelly on the Clue Crew stands outside Independence Hall at Independence National Historical Park in Philadelphia, PA.) In 1765 the streets outside Independence Hall were packed with people protesting this act that placed levies on newspapers, playing cards & pamphlets","response":"the Stamp Act","value":600,"isDailyDouble":false},{"clue":"(Kelly of the Clue Crew stands with the Liberty Bell at Independence National Historical Park in Philadelphia, PA.) Though the bell first rang out in 1753, the term \"Liberty Bell\" wasn't used until 1839 in a poem fittingly found in this abolitionist's newspaper, \"The Liberator\\\"","response":"William Lloyd Garrison","value":800,"isDailyDouble":false},{"clue":"(Kelly of the Clue Crew shows us a Classical/Revival style building in Independence National Historical Park in Philadelphia, PA.) Madison & Jefferson were opposed, but Hamilton's vision of a strong central government, in economics as well as politics, won out & this financial institution was created in 1791, headquartered here in Philadelphia","response":"the Bank of the United States","value":1000,"isDailyDouble":false}]},{"name":"HODGEPODGE","clues":[{"clue":"A digestive enzyme called bromelain comes from this Hawaiian fruit","response":"pineapple","value":200,"isDailyDouble":false},{"clue":"This heavily armored Union warship was said to look like a \"cheese box on a raft\\\"","response":"the Monitor","value":400,"isDailyDouble":false},{"clue":"One explanation for this Penn. nickname is that it's centrally located among the 13 original states","response":"\\\"The Keystone State\\\"","value":600,"isDailyDouble":false},{"clue":"In 1892 a Denver lawyer created this breakfast cereal, using a machine that pressed wheat into thin strips","response":"Shredded Wheat","value":800,"isDailyDouble":false},{"clue":"Capitoline, Quirinal, Viminal, Esquiline, Caelian, Aventine & Palatine","response":"the seven hills of Rome","value":1000,"isDailyDouble":false}]},{"name":"ZEBRAS","clues":[{"clue":"Only continent to which zebras are native","response":"Africa","value":200,"isDailyDouble":false},{"clue":"TV sitcom on which the main character called his racially mixed daughter-in-law a zebra","response":"The Jeffersons","value":400,"isDailyDouble":false},{"clue":"In England, a deer crossing is for deer, but a zebra crossing is for these","response":"pedestrians","value":600,"isDailyDouble":false},{"clue":"Professional sport in which 7 \"zebras\" officiate","response":"football","value":800,"isDailyDouble":false},{"clue":"In Simon & Garfunkel's 1967 song, \"At the Zoo\", zebras are said to have these political views","response":"reactionary","value":1000,"isDailyDouble":false}]},{"name":"FRANCE","clues":[{"clue":"Local languages besides French include Provencal in Provence & this in Flanders","response":"Flemish","value":200,"isDailyDouble":false},{"clue":"A part-iridium cylinder in France is the standard for this metric unit of mass (about 2.2 pounds)","response":"a kilogram","value":400,"isDailyDouble":false},{"clue":"(Sarah gives the clue from Omaha Beach.) The amphibious assault on Normandy took place at five beaches. The British landed at Gold and Sword, the Canadians at Juno, and the Americans at Omaha Beach and this beach to the west","response":"Utah","value":600,"isDailyDouble":false},{"clue":"The oldest society of the Institut de France, it published its first dictionary in 1694","response":"the (French) Academy","value":800,"isDailyDouble":false},{"clue":"In 1848 Louis Napoleon Bonaparte was elected president; in 1852 he took this name as Emperor","response":"Napoleon III","value":1000,"isDailyDouble":false}]},{"name":"THE 1920s","clues":[{"clue":"This type of mail service linked New York & San Francisco in 1920","response":"airmail","value":200,"isDailyDouble":false},{"clue":"In 1929 King Alexander changed the name of his country to this, the \"land of the South Slavs\\\"","response":"Yugoslavia","value":400,"isDailyDouble":false},{"clue":"Doubling was added to this ancient game around 1925","response":"backgammon","value":600,"isDailyDouble":false},{"clue":"Wilhelm Roentgen, the first Nobel laureate in this category, died in 1923","response":"physics","value":800,"isDailyDouble":true},{"clue":"This most populous Alaskan city was incorporated in 1920","response":"Anchorage","value":1000,"isDailyDouble":false}]},{"name":"POETRY","clues":[{"clue":"Byron called this animal \"the firmest friend, the first to welcome, foremost to defend\\\"","response":"dog","value":200,"isDailyDouble":false},{"clue":"Two lines of rhyming verse that are self-contained in meaning & structure","response":"couplet","value":400,"isDailyDouble":false},{"clue":"Poem that states, \"Fair tresses man's imperial race ensnare, and beauty draws us with a single hair.\\\"","response":"The Rape of the Lock","value":600,"isDailyDouble":true},{"clue":"Native of Lesbos known for the lyric poetry she wrote to the girls she led","response":"Sappho","value":800,"isDailyDouble":false},{"clue":"\\\"Boomlay, boomlay, boomlay, boom\" is a recurring line in V. Lindsay's poem about this part of Africa","response":"the Congo","value":1000,"isDailyDouble":false}]},{"name":"C.S., I","clues":[{"clue":"Money matters at this investment service company that invites you to \"Talk to Chuck\\\"","response":"Charles Schwab","value":200,"isDailyDouble":false},{"clue":"This astronomer & science writer from Cornell helped select the Mars landing sites for the Viking probes","response":"Carl Sagan","value":400,"isDailyDouble":false},{"clue":"Some say when it comes to his films \"Heathers\" & \"Pump Up the Volume\", it's better to shoot first, then ask this actor","response":"(Christian) Slater","value":600,"isDailyDouble":false},{"clue":"He became New York's senior senator when Daniel Patrick Moynihan retired in 2001","response":"(Charles) Schumer","value":800,"isDailyDouble":false},{"clue":"In 1914 a group of his \"Chicago Poems\" appeared in Poetry magazine","response":"Carl Sandburg","value":1000,"isDailyDouble":false}]},{"name":"U.S. GEOGRAPHY","clues":[{"clue":"The Great Salt Lake desert covers about 4,000 square miles in this state","response":"Utah","value":200,"isDailyDouble":false},{"clue":"This city that's home to the University of Colorado lies at the base of the Flatiron Range of the Rockies","response":"Boulder","value":400,"isDailyDouble":false},{"clue":"Edgartown & Oak Bluffs are 2 of only a handful of towns on this island in New England","response":"Martha's Vineyard","value":600,"isDailyDouble":false},{"clue":"It sounds like a daily paper but this port city is actually part of a metro area that includes Norfolk & Virginia Beach","response":"Newport News","value":800,"isDailyDouble":false},{"clue":"Niagara Falls is made up of 2 falls, the American falls & these Canadian falls","response":"Horseshoe Falls","value":1000,"isDailyDouble":false}]},{"name":"PRESIDENTIAL TRIVIA","clues":[{"clue":"As an Illinois Congressman, he attended the inaugural ball of Zachary Taylor","response":"Abraham Lincoln","value":200,"isDailyDouble":false},{"clue":"The lyrics for it come from Sir Walter Scott's \"The Lady of the Lake\\\"","response":"\\\"Hail to the Chief\\\"","value":400,"isDailyDouble":false},{"clue":"In 1809 he became the 1st president inaugurated wearing only American-made clothes","response":"James Madison","value":600,"isDailyDouble":false},{"clue":"The 1st time a president left the U.S. while in office was when T. Roosevelt went to inspect this","response":"Panama Canal","value":800,"isDailyDouble":true},{"clue":"More presidents have been affiliated with this high church denomination than any other","response":"Episcopalian","value":1000,"isDailyDouble":false}]},{"name":"HAIKU ABOUT THE POET","clues":[{"clue":"Born in Beatrice / Worshiped a girl named Florence / Oops, got that backwards","response":"Dante","value":200,"isDailyDouble":false},{"clue":"\\\"Queen Mab\" was so fab / Was the groom of Frankenstein / Not waving, drowning","response":"Percy Shelley","value":400,"isDailyDouble":false},{"clue":"Talkin' 'bout lilacs / A Civil War caregiver / The good gray poet","response":"(Walt) Whitman","value":600,"isDailyDouble":false},{"clue":"\\\"Aurora Leigh\", whoa! / 19th century lady / Let me count the ways","response":"Elizabeth Barrett Browning","value":800,"isDailyDouble":false},{"clue":"A joy forever / Big \"into Chapman's Homer\" / Tuberculosis","response":"Keats","value":1000,"isDailyDouble":false}]},{"name":"PIES","clues":[{"clue":"Though a pie is served from its baking dish, this tiny cousin is removed from its dish","response":"tart","value":200,"isDailyDouble":false},{"clue":"Shepherd's pie is actually an entree originally made with this meat","response":"lamb","value":400,"isDailyDouble":false},{"clue":"If you want your pie crust to be flaky, choose this ingredient carefully","response":"shortening","value":600,"isDailyDouble":false},{"clue":"This type of pie, like chocolate, can simply be pudding in a pie shell","response":"custard (cream pie)","value":800,"isDailyDouble":false},{"clue":"The earliest recipe for this pie filling of finely chopped apples, spices & suet dates from 1486","response":"mincemeat","value":1000,"isDailyDouble":false}]},{"name":"ON THE 2018 BILLBOARD CHARTS","clues":[{"clue":"This co-worker of Adam, Alicia & Kelly climbed the country chart with \"I Lived It\\\"","response":"Blake Shelton","value":200,"isDailyDouble":false},{"clue":"This \"Slippery When Wet\" band entered the Rock & Roll Hall of Fame & were on the charts with \"This House Is Not For Sale\\\"","response":"Bon Jovi","value":400,"isDailyDouble":false},{"clue":"Lil Pump was quite insistent about this \"gang\", this \"gang\", this \"gang\", this \"gang\", this \"gang\"...","response":"\\\"Gucci Gang\\\"","value":600,"isDailyDouble":false},{"clue":"Weezer remade a No. 1 song by Toto that says, \"I bless the rains down in\" this place","response":"Africa","value":800,"isDailyDouble":false},{"clue":"Yes, admiral! Turns out this one-named \"Bad At Love\" singer is good at music","response":"Halsey","value":1000,"isDailyDouble":false}]},{"name":"\\\"ARG\\\"","clues":[{"clue":"This type of plane carries packages, not passengers","response":"cargo","value":200,"isDailyDouble":false},{"clue":"The FDA requires that this butter substitute be fortified with Vitamin A","response":"margarine","value":400,"isDailyDouble":false},{"clue":"It's a signal by bugle for the soldiers to attack","response":"charge","value":600,"isDailyDouble":false},{"clue":"This city was named for one of the founders of American Express","response":"Fargo","value":800,"isDailyDouble":false},{"clue":"It's the lingo peculiar to a particular trade or group","response":"jargon","value":1000,"isDailyDouble":false}]},{"name":"WORLD CAPITALS","clues":[{"clue":"Only about 4,000 people lived in this Greek city when it was recaptured from the Turks in 1833","response":"Athens","value":200,"isDailyDouble":false},{"clue":"This Asian city needed major rebuilding after the earthquake & fire of 1923, & again after WWII","response":"Tokyo","value":400,"isDailyDouble":false},{"clue":"Via del Corso, the main street of this capital, is named for the horse races once run there","response":"Rome","value":600,"isDailyDouble":false},{"clue":"The golden stupa in the Shwe Dagon Pagoda is the most notable building in this city Burmese call Yangon","response":"Rangoon","value":800,"isDailyDouble":false},{"clue":"In this Arab capital Christians live mainly on the east side & Muslims mainly on the west side","response":"Beirut","value":1000,"isDailyDouble":false}]},{"name":"ADJECTIVES OF THE YOUNG AND THE RESTLESS","clues":[{"clue":"\\\"Abby, I hear The Naked Heiress is gonna be on Jeopardy! that's huge!\" \"Mom, please. I am rich and famous.\" [Sighs] \"Honey, don't you think you're being...\" ...this adjective that means \"world-weary\" & \"cynical\"—it doesn't mean \"covered in green gemstones\\\"","response":"jaded","value":200,"isDailyDouble":false},{"clue":"\\\"We can never do this again. Nobody, and I mean nobody, can know about it.\" \"Tres romantic, Nick. What are you implying, that I'm not...\" ...this 11-letter adjective meaning reliable & responsible like a Boy Scout","response":"trustworthy","value":400,"isDailyDouble":false},{"clue":"\\\"Please, Lily, understand, everything I did was to keep you and the twins safe.\" \"Cane, you pretended that you were dead and made me think that I was sleeping with a ghost. I ended up in an insane asylum. You're...\" ...this 10-letter adjective from the Latin for \"look down on\" (& favored by Daffy Duck on occasion)","response":"despicable","value":600,"isDailyDouble":false},{"clue":"\\\"Oh, Jack, it feels just like yesterday that you and Diane and I were celebrating the IPO.\" \"I've had my eye on you since before Diane died, and now I have even more reason to be...\" ...this doubtful word that's in the title of Elvis' last No. 1 pop hit","response":"suspicious","value":800,"isDailyDouble":false},{"clue":"\\\"Dear God. You manipulate everyone around you, just like a marionette. You are downright...\" ...this adjective, also the title of a hit Broadway musical that features Munchkins & flying monkeys","response":"wicked","value":1000,"isDailyDouble":false}]},{"name":"CROSSWORD CLUES \"P\\\"","clues":[{"clue":"Manicotti or macaroni (5)","response":"Pasta","value":200,"isDailyDouble":false},{"clue":"Pilgrims' stepping stone (8,4)","response":"Plymouth Rock","value":400,"isDailyDouble":false},{"clue":"Coffin carrier (10)","response":"Pallbearer","value":600,"isDailyDouble":false},{"clue":"A seedy fruit (11)","response":"Pomegranate","value":800,"isDailyDouble":true},{"clue":"Ahab's vessel (6)","response":"Pequod","value":1000,"isDailyDouble":false}]},{"name":"HIGHEST-RATED TV SERIES OF THE SEASON","clues":[{"clue":"1982-83 & 1992-93: This newsmagazine","response":"60 Minutes","value":200,"isDailyDouble":false},{"clue":"2004-05: This drama—the original one, not New York or Miami","response":"CSI","value":400,"isDailyDouble":false},{"clue":"1969-70: This show featuring Goldie Hawn, Ruth Buzzi & Gary Owens","response":"Laugh-In","value":600,"isDailyDouble":false},{"clue":"1957-58 & the next 3 seasons: This Western set in Dodge City","response":"Gunsmoke","value":800,"isDailyDouble":false},{"clue":"1971-72 & the next 4 seasons: Those were the days","response":"All in the Family","value":1000,"isDailyDouble":false}]},{"name":"IT'S ALL IN THE GAME","clues":[{"clue":"Queen, rook, pawn, knight","response":"chess","value":200,"isDailyDouble":false},{"clue":"Free Parking, Reading Railroad, Community Chest","response":"Monopoly","value":400,"isDailyDouble":false},{"clue":"Letter tiles, double word score space, triple word score space","response":"Scrabble","value":600,"isDailyDouble":false},{"clue":"Lead pipe, kitchen, Colonel Mustard","response":"Clue","value":800,"isDailyDouble":false},{"clue":"Water on the knee, bread basket, writer's cramp","response":"Operation","value":1000,"isDailyDouble":false}]},{"name":"WHERE ARE YOU WEARING?","clues":[{"clue":"An island in the Bay of Naples gave its name to these 3/4-length pants","response":"capris","value":200,"isDailyDouble":false},{"clue":"This state precedes \"hunting shoe\" in the name of the first product introduced by L.L. Bean","response":"Maine","value":400,"isDailyDouble":false},{"clue":"A wide cuff folded back & fastened with a cuff link","response":"a French cuff","value":600,"isDailyDouble":false},{"clue":"This red felt hat is named for a town in Morocco","response":"fez","value":800,"isDailyDouble":false},{"clue":"Dotted patterns are common on the fabric known as this muslin","response":"Swiss muslin","value":1000,"isDailyDouble":false}]},{"name":"LIKE A BOSS","clues":[{"clue":"Cornell's Tech Campus on New York's Roosevelt Island got a $100 million donation from this ex-mayor, now back in business","response":"Bloomberg","value":200,"isDailyDouble":false},{"clue":"After Hewlett-Packard parted ways with this woman in 2005, she got paid like a boss, with a $21 million severance","response":"(Carly) Fiorina","value":400,"isDailyDouble":false},{"clue":"Running up the score before halftime, Amazon's strong 2nd quarter in 2015 helped put an extra $16.5 bil. in this CEO's pocket","response":"(Jeff) Bezos","value":600,"isDailyDouble":false},{"clue":"NPR fans know Harvard Business Review listed the CEO of Novo this as 2015's best-performing CEO in the world","response":"Nordisk","value":800,"isDailyDouble":false},{"clue":"In 2015 this ex-Microsoft man & L.A. Clippers owner was the richest sports team owner in the U.S., with $21.6 billion","response":"Steve Ballmer","value":1000,"isDailyDouble":false}]},{"name":"SPORTS STARS","clues":[{"clue":"In his first year as a coach, this former Celtic led the Pacers to their best NBA record ever","response":"Larry Bird","value":200,"isDailyDouble":false},{"clue":"The first U.S. tennis player to win $100,000 in a year, in 1975 he became the first black man to win at Wimbledon","response":"Arthur Ashe","value":400,"isDailyDouble":false},{"clue":"(Hi, I'm Bob Costas.) In 1956 this N.Y. Yankee became the only player ever to win baseball's Triple Crown while hitting more than 50 home runs","response":"Mickey Mantle","value":600,"isDailyDouble":false},{"clue":"College football's Butkus Award is named for Dick Butkus, a 6-time all-pro for this NFL team","response":"Chicago Bears","value":800,"isDailyDouble":false},{"clue":"In 1998 this flamboyant Italian skier won the 50th World Cup race of his career","response":"Alberto Tomba","value":1000,"isDailyDouble":false}]},{"name":"MARCONI & CHEESE","clues":[{"clue":"Perhaps trying to spell \"Swiss cheese\" in 1901, Marconi telegraphed the letter \"S\" via this code","response":"Morse code","value":200,"isDailyDouble":false},{"clue":"Perhaps some Argentinean Sardo filled Guglielmo up in this capital as he received radio messages from Ireland in 1910","response":"Buenos Aires","value":400,"isDailyDouble":false},{"clue":"Marconi likely sampled some Brie when he acted as plenipotentiary at the 1919 peace conference at this royal residence","response":"Versailles","value":600,"isDailyDouble":false},{"clue":"An American cheese sandwich would've been a just reward for Marconi in 1899 after he followed this yacht race by radio","response":"America's Cup","value":800,"isDailyDouble":false},{"clue":"Marconi was first educated in this Italian city, also a meat that could go well on a sandwich with a nice fontina","response":"Bologna","value":1000,"isDailyDouble":false}]},{"name":"I LED WHAT CABINET DEPARTMENT?","clues":[{"clue":"To put it diplomatically, Condoleezza Rice","response":"State","value":200,"isDailyDouble":false},{"clue":"Alexander Hamilton; now say the phrase that pays!","response":"Treasury","value":400,"isDailyDouble":false},{"clue":"William Willard Wirtz won workers' well-wishes","response":"Labor","value":600,"isDailyDouble":false},{"clue":"Janet Napolitano, who as president of the University of California later sued this department over its treatment of \"dreamers\\\"","response":"Homeland Security","value":800,"isDailyDouble":false},{"clue":"George Dern, doing good work on preparedness in the 1930s in a job that no longer exists","response":"Secretary of War","value":1000,"isDailyDouble":false}]},{"name":"STATE CAPITALS","clues":[{"clue":"Until 1875 its dual capitals were New Haven & Hartford","response":"Connecticut","value":200,"isDailyDouble":false},{"clue":"This N.M. town is the oldest city that's a state capital","response":"Santa Fe","value":400,"isDailyDouble":false},{"clue":"Crossing the Delaware on Xmas, 1776, Washington defeated the Hessians at this N.J. capital","response":"Trenton, New Jersey","value":600,"isDailyDouble":false},{"clue":"It actually is 5,280 ft. above sea level","response":"Denver","value":800,"isDailyDouble":false},{"clue":"The name shows its founder, Roger Williams, believed God led him there","response":"Providence","value":1000,"isDailyDouble":false}]},{"name":"FIRST NAME'S THE SAME","clues":[{"clue":"Cash, Depp","response":"Johnny","value":200,"isDailyDouble":false},{"clue":"Bakula, Wolf","response":"Scott","value":400,"isDailyDouble":false},{"clue":"Carey, Bledsoe","response":"Drew","value":600,"isDailyDouble":false},{"clue":"Lillard, Modine","response":"Matthew","value":800,"isDailyDouble":false},{"clue":"Connelly, Garner, Holliday","response":"Jennifer","value":1000,"isDailyDouble":false}]},{"name":"BUTCH CASSIDY","clues":[{"clue":"Harry Longabaugh, Butch's sometime partner, was better known by this nickname","response":"the Sundance Kid","value":200,"isDailyDouble":false},{"clue":"Butch's first big crime was the $20,000 holdup of the San Miguel Valley Bank in Telluride in this state in 1889","response":"Colorado","value":400,"isDailyDouble":false},{"clue":"Name of the gang Butch led on numerous rampages, or a 1969 Peckinpah film","response":"The Wild Bunch","value":600,"isDailyDouble":false},{"clue":"Detectives from this private agency chased Butch out of the country in 1901","response":"the Pinkertons","value":800,"isDailyDouble":false},{"clue":"Butch was reportedly killed near San Vicente in this country in 1909, though no one knows for sure","response":"Bolivia","value":1000,"isDailyDouble":false}]},{"name":"COLLEGES","clues":[{"clue":"The best known \"Longhorns\" in Austin attend this","response":"University of Texas","value":200,"isDailyDouble":false},{"clue":"College in whose Sorin Hall Michael & John Shea wrote the following in 1908: [instrumental music plays]","response":"University of Notre Dame","value":400,"isDailyDouble":true},{"clue":"Some scenes in \"The Exorcist\" take place & were shot at this D.C. university","response":"Georgetown","value":600,"isDailyDouble":false},{"clue":"To end confusion with African maned lion, this school sports a 13-ton statue of a Nittany lion","response":"Penn State","value":800,"isDailyDouble":false},{"clue":"Originally endowed by philanthropist Peter Cooper, this NYC private college is still tuition-free","response":"Cooper Union","value":1000,"isDailyDouble":false}]},{"name":"DIAMONDS","clues":[{"clue":"A diamond's weight is expressed in these units, which equal about 1/142 ounce","response":"carats","value":200,"isDailyDouble":false},{"clue":"This famous blue diamond in the Smithsonian was probably cut from a stone stolen during the French Revolution","response":"the Hope Diamond","value":400,"isDailyDouble":false},{"clue":"The Cullinan, the world's largest diamond, was discovered in this present country in 1905","response":"South Africa","value":600,"isDailyDouble":false},{"clue":"The 4 factors for grading & pricing a diamond are weight, clarity, cut & this","response":"color","value":800,"isDailyDouble":false},{"clue":"Dating back to the 1600s, this 58-facet cut is the most popular for diamonds","response":"the brilliant","value":1000,"isDailyDouble":false}]},{"name":"ARCHAEOLOGY","clues":[{"clue":"Archaeologists are busy on Mount Lykaion & in a cave on Crete, 2 supposed birthplaces of this Greek ruler god","response":"Zeus","value":200,"isDailyDouble":false},{"clue":"10,000-year-old seeds of this gourd have been found in Peru, where the veggie originated","response":"a pumpkin (or squash)","value":400,"isDailyDouble":false},{"clue":"Archaeologists have found Vespasian's country house—or as he'd have called it in Latin, this 5-letter word","response":"a villa","value":600,"isDailyDouble":false},{"clue":"Thermo-luminescence is a technique used to establish this for items exposed to heat, like fireplace stones","response":"its date","value":800,"isDailyDouble":false},{"clue":"(Sarah of the Clue Crew shows a stone sculpture on the monitor.) At Saqqra, Egypt, & probably from around 2500 B.C., the seated this worker was found; he still has his papyrus roll, but someone took his brush","response":"a scribe","value":1000,"isDailyDouble":false}]},{"name":"MUSEUMS","clues":[{"clue":"The Old Mint in this city features jazz & Mardi Gras memorabilia","response":"New Orleans","value":200,"isDailyDouble":false},{"clue":"In 1987 this NYC museum added the Sackler Galleries for Asian Art","response":"the Metropolitan Museum","value":400,"isDailyDouble":false},{"clue":"The Columbia River Maritime Museum in Astoria in this state has exhibits on the salmon industry","response":"Oregon","value":600,"isDailyDouble":false},{"clue":"The Goodyear World of Rubber in this city has exhibits depicting the history of rubber","response":"Akron","value":800,"isDailyDouble":false},{"clue":"Exhibits at the Salvation Army's Heritage Centre in London include this man's Bible & passport","response":"General Booth","value":1000,"isDailyDouble":false}]},{"name":"THE SALE MAKER","clues":[{"clue":"In this billionaire's words, \"In 1970 I founded Virgin as a mail order record retailer\\\"","response":"Richard Branson","value":200,"isDailyDouble":false},{"clue":"He was a traveling soap salesman before founding what became the world's largest chewing gum company","response":"Wrigley","value":400,"isDailyDouble":false},{"clue":"In 1912 he was the Maine (& only) man in his new clothing business; today, the company has annual sales of $1.5 billion","response":"L.L. Bean","value":600,"isDailyDouble":false},{"clue":"The founder of Ronco, he pioneered the infomercial","response":"Ron Popeil","value":800,"isDailyDouble":false},{"clue":"John Patterson, CEO of NCR, this company, was one of the first to make use of sales training & retreats","response":"National Cash Register","value":1000,"isDailyDouble":false}]},{"name":"A & _","clues":[{"clue":"The first frosty mug of the root beer now sold under this name was bought in California in 1919","response":"A&W","value":200,"isDailyDouble":false},{"clue":"\\\"Jeopardy!\" would fall under this game show format, the reverse of normal","response":"A&Q","value":400,"isDailyDouble":false},{"clue":"The online Biography.com is a service of this cable channel","response":"A&E","value":600,"isDailyDouble":false},{"clue":"Lyle Lovett is a grad of this Texas university","response":"Texas A&M","value":800,"isDailyDouble":false},{"clue":"This supermarket chain began back in 1859 as a bulk tea merchandiser","response":"A&P (Atlantic & Pacific)","value":1000,"isDailyDouble":false}]},{"name":"A SPACE ODDITY","clues":[{"clue":"The surface of Jupiter's moon Io is continually re-formed by flows of this, hotter than the same stuff on Earth","response":"lava","value":200,"isDailyDouble":false},{"clue":"When real, this phenomenon is caused by atmospheric dust; when part of a metaphor, it refers to a rarity","response":"a blue moon","value":400,"isDailyDouble":false},{"clue":"(Sarah of the Clue Crew presents the clue.) The pale blue dot off in the distance that is dwarfed by Saturn's rings is actually Earth, & the photo was taken from this orbiter with an Italian name","response":"Cassini","value":600,"isDailyDouble":false},{"clue":"Astronaut Chris Hadfield revealed they don't do laundry in space, they eject old clothes & this happens to them","response":"they burn on re-entry","value":800,"isDailyDouble":false},{"clue":"(Kelly of the Clue Crew presents the clue.) A pillar was formed by radiation and charged particles from stars within the Carina one of these","response":"a nebula","value":1000,"isDailyDouble":false}]},{"name":"FASTENERS","clues":[{"clue":"One can hold a stamp in an album or a door to its frame","response":"a hinge","value":200,"isDailyDouble":false},{"clue":"It's 2 strips, one with nylon hooks & the other with nylon pile","response":"Velcro","value":400,"isDailyDouble":false},{"clue":"Working on a vacuum principle, they hold your Garfield doll to your car window","response":"a suction cup","value":600,"isDailyDouble":false},{"clue":"Its name might have come from the Latin \"scrofa\" meaning \"sow\", since its threads look like a sow's tail","response":"a screw","value":800,"isDailyDouble":false},{"clue":"The long metal pin that holds your shish kebab together","response":"a skewer","value":1000,"isDailyDouble":false}]},{"name":"STOCK SYMBOL SHOPPING","clues":[{"clue":"Before the parade passes by, do some shopping here: M","response":"Macy's","value":200,"isDailyDouble":false},{"clue":"Set your GPS for this retailer that also owns Old Navy: GPS","response":"Gap","value":400,"isDailyDouble":false},{"clue":"For a new pair of Nikes or Pumas: FL","response":"Foot Locker","value":600,"isDailyDouble":false},{"clue":"Guys, \"you're going to like the way you look\": MW","response":"Men's Wearhouse","value":800,"isDailyDouble":false},{"clue":"For all your Xbox & PlayStation needs: GME","response":"GameStop","value":1000,"isDailyDouble":false}]},{"name":"\\\"LAST\" MOVIES","clues":[{"clue":"The Band's 1st film & final concert","response":"The Last Waltz","value":200,"isDailyDouble":false},{"clue":"Smooth-talking Robt. Preston recruited this teenage galaxy saver","response":"The Last Starfighter","value":400,"isDailyDouble":false},{"clue":"See decadence! see persecution! see Vesuvius erupt!!!","response":"The Last Days of Pompeii","value":600,"isDailyDouble":false},{"clue":"Peter Bogdanovich's somber '71 tale of Texas","response":"The Last Picture Show","value":800,"isDailyDouble":false},{"clue":"Neil Simon's middle class, middle-aged Don Juan","response":"The Last of the Red Hot Lovers","value":1000,"isDailyDouble":false}]},{"name":"THE BOYS IN BLUE","clues":[{"clue":"This federal police agency is abbreviated the DEA","response":"Drug Enforcement Administration","value":200,"isDailyDouble":false},{"clue":"Encarta reports that with over 96,000 this state has more full-time law enforcement employees than any other","response":"California","value":400,"isDailyDouble":false},{"clue":"Robert Stack & Kevin Costner have both played this crusading T-Man","response":"Eliot Ness","value":600,"isDailyDouble":false},{"clue":"This international group founded in 1923 helps police in one country communicate with those of another","response":"Interpol","value":800,"isDailyDouble":false},{"clue":"Guidelines for sheriffs & village constables were established in this important document in 1215","response":"Magna Carta","value":1000,"isDailyDouble":false}]},{"name":"THE BOURGEOISIE","clues":[{"clue":"This 1848 writing team popularized the word bourgeoisie for the middle class that controlled the means of production","response":"Marx & Engels","value":200,"isDailyDouble":false},{"clue":"This French word for \"small\" is used of small businessmen, civil servants & others aspiring to be haut-bourgeois","response":"petite","value":400,"isDailyDouble":false},{"clue":"An essential part of the 19th century German decor called biedermeier was one of these, ein klavier","response":"a piano","value":600,"isDailyDouble":false},{"clue":"This relaxing residence is a common bourgeois possession; the film \"The Discreet Charm of the Bourgeoisie\" is set in one","response":"a chateau (country home)","value":800,"isDailyDouble":false},{"clue":"David Brooks dubbed those who combine nice possessions & hippie values \"Bobos\", short for bourgeois these","response":"Bohemians","value":1000,"isDailyDouble":false}]},{"name":"1999 COMMENCEMENT SPEAKERS","clues":[{"clue":"Texas A&M grads got this former U.S. president telling them to \"Dream Big\\\"","response":"George H.W. Bush","value":200,"isDailyDouble":false},{"clue":"Hey, hey, hey! He told Colgate grads that whining won't get you your way anymore","response":"Bill Cosby","value":400,"isDailyDouble":false},{"clue":"At the U. of Richmond this retired general stormed on about how character is what counts in leadership","response":"Norman Schwarzkopf","value":600,"isDailyDouble":false},{"clue":"He told Vassar grads, \"May the force be with you; hey, he could have said, \"This is CNN\\\"","response":"James Earl Jones","value":800,"isDailyDouble":true},{"clue":"This \"China Girl\" singer joked at a music school, \"How does a tuba player answer the telephone? Hello, Domino's\\\"","response":"David Bowie","value":1000,"isDailyDouble":false}]},{"name":"TIME FOR CLASS","clues":[{"clue":"P.E.: Practice hard to become a Hall of Famer in this sport, like Cal Ripken Jr.","response":"baseball","value":200,"isDailyDouble":false},{"clue":"Science: \"Rover\" around & discover that a \"year\" on this planet lasts 687 days","response":"Mars","value":400,"isDailyDouble":false},{"clue":"Shop: No, you will most certainly not be working with the gas-flame device called an acetylene this","response":"torch","value":600,"isDailyDouble":false},{"clue":"French: \"Le livre est sur la table\" means this is on the table; pick it up & start learning","response":"the book","value":800,"isDailyDouble":false},{"clue":"English: Learn that he left Princeton without a degree in 1917 & 8 years later penned \"The Great Gatsby\\\"","response":"F. Scott Fitzgerald","value":1000,"isDailyDouble":false}]},{"name":"\\\"E\" FOR EFFORT","clues":[{"clue":"This joint connects your upper arm to your forearm","response":"Elbow","value":200,"isDailyDouble":false},{"clue":"On \"The Simpsons\", Mr. Burns usually uses this word when he finds something superb or first-rate","response":"\\\"Excellent!\\\"","value":400,"isDailyDouble":false},{"clue":"This verb means to sneak off & get married","response":"Elope","value":600,"isDailyDouble":false},{"clue":"The solar type of this event happens when the moon comes between the sun & the Earth","response":"Eclipse","value":800,"isDailyDouble":false},{"clue":"For this Mexican dish, roll some meat & cheese in a corn tortilla & bake the \"whole\" thing","response":"Enchiladas","value":1000,"isDailyDouble":false}]},{"name":"STATELY PRECEDERS","clues":[{"clue":"Peach or O'Keeffe","response":"Georgia","value":200,"isDailyDouble":false},{"clue":"Waltz or walking horse","response":"Tennessee","value":400,"isDailyDouble":false},{"clue":"Hot dog or J. Frog","response":"Michigan","value":600,"isDailyDouble":false},{"clue":"Man (of weird news fame) or Panther","response":"Florida","value":800,"isDailyDouble":false},{"clue":"\\\"Dreamin'\" or roll","response":"California","value":1000,"isDailyDouble":false}]},{"name":"TRADITIONAL ANNIVERSARY GIFTS","clues":[{"clue":"The 8th: This alloy, so maybe use one of your old Olympic medals","response":"bronze","value":200,"isDailyDouble":false},{"clue":"The 35th: This marine organism, so be creative & take a trip to the Great Barrier Reef","response":"coral","value":400,"isDailyDouble":false},{"clue":"The 11th: This metal, so anything Superman-related","response":"steel","value":600,"isDailyDouble":false},{"clue":"The 2nd: This fiber, so how about a set of sheets with a high thread count","response":"cotton","value":800,"isDailyDouble":false},{"clue":"The 30th: These gems, perhaps a string of the seed type","response":"pearls","value":1000,"isDailyDouble":false}]},{"name":"ABBREVIATED","clues":[{"clue":"A \"green\" government group: EPA","response":"Environmental Protection Agency","value":200,"isDailyDouble":false},{"clue":"High-ranking business operative: CFO","response":"chief financial officer","value":400,"isDailyDouble":false},{"clue":"An international alliance: EU","response":"the European Union","value":600,"isDailyDouble":false},{"clue":"On an accountant's calendar: FY","response":"fiscal year","value":800,"isDailyDouble":false},{"clue":"Sometimes you get extras with one of these: DVD","response":"digital video disc","value":1000,"isDailyDouble":false}]},{"name":"WALLS","clues":[{"clue":"Due to student unrest, Gorbachev's May 17,1989 visit to this famous wall was hardly noted","response":"the Great Wall of China","value":200,"isDailyDouble":false},{"clue":"City in which you'd see the following wall","response":"Jerusalem","value":400,"isDailyDouble":true},{"clue":"CErvantes & Tennyson both warned \"Walls have\" these","response":"ears","value":600,"isDailyDouble":false},{"clue":"In 1979 Pink Floyd released an album called \"The Wall\", & he had one called \"Off the Wall\\\"","response":"Michael Jackson","value":800,"isDailyDouble":false},{"clue":"According to Richard Lovelace, \"Stone walls do not make\" one of these","response":"a prison","value":1000,"isDailyDouble":false}]},{"name":"DINO","clues":[{"clue":"The name of dinosaurs known as ornithopods tells us they had feet shaped like those of these creatures","response":"birds","value":200,"isDailyDouble":false},{"clue":"Archaeological evidence suggests this 3-horned dinosaur may have been the last to survive before extinction","response":"Triceratops","value":400,"isDailyDouble":false},{"clue":"NBA fans in this city cheer on a team represented by a speedy dinosaur of the late Cretaceous period","response":"Toronto","value":600,"isDailyDouble":true},{"clue":"The 90-foot Diplodocus weighed 10 tons, 1/8 as much as some shorter dinos, because its bones were this","response":"hollow","value":800,"isDailyDouble":false},{"clue":"\\\"Sue\", the skeleton of this creature, is an attraction at Chicago's Field Museum","response":"Tyrannosaurus rex","value":1000,"isDailyDouble":false}]},{"name":"MOVIE TIMES","clues":[{"clue":"James Franco played a mountain climber pinned by a rock in this 2010 fact-based drama","response":"127 Hours","value":200,"isDailyDouble":false},{"clue":"Gary Cooper was Marshal Will Kane in this classic","response":"High Noon","value":400,"isDailyDouble":false},{"clue":"Bookish CIA researcher Robert Redford is thrust into a conspiracy in this 1975 thriller","response":"Three Days of the Condor","value":600,"isDailyDouble":false},{"clue":"Joseph Gordon-Levitt has his heart broken by Zooey Deschanel in this indie film, but autumn arrives in due time","response":"(500) Days of Summer","value":800,"isDailyDouble":false},{"clue":"Sandra Bullock finds she can quit Hugh Grant in this 2002 romantic comedy","response":"Two Weeks Notice","value":1000,"isDailyDouble":false}]},{"name":"READ ANY GOOD BOOKS?","clues":[{"clue":"Holden Caulfield is the narrator of this novel","response":"\\\"Catcher in the Rye\\\"","value":200,"isDailyDouble":false},{"clue":"He followed \"The Seven Spiritual Laws of Success\" with \"The Seven Spiritual Laws for Parents\\\"","response":"Deepak Chopra","value":400,"isDailyDouble":false},{"clue":"2 from this romance publisher are \"The Amorous Heiress\" & \"The Madcap Heiress\\\"","response":"Harlequin","value":600,"isDailyDouble":false},{"clue":"This character is the young man in Joyce's \"A Portrait of the Artist as a Young Man\\\"","response":"Stephen Dedalus","value":800,"isDailyDouble":false},{"clue":"Billie Letts' \"Where the Heart Is\" opens with Novalee Nation stranded in Oklahoma at this discount store","response":"Wal-Mart","value":1000,"isDailyDouble":false}]},{"name":"\\\"NEW\" YORK","clues":[{"clue":"Someone recently married","response":"a newlywed","value":200,"isDailyDouble":false},{"clue":"1980s bands like The B-52's are classified as this style of music","response":"New Wave","value":400,"isDailyDouble":false},{"clue":"It starts with the Book of Matthew & ends with the Book of Revelation","response":"the New Testament","value":600,"isDailyDouble":false},{"clue":"The largest city in New Jersey","response":"Newark","value":800,"isDailyDouble":false},{"clue":"St. John's is the capital city of this Canadian province","response":"Newfoundland","value":1000,"isDailyDouble":false}]},{"name":"RIVERS","clues":[{"clue":"As a baby Moses was left in a basket along this river's banks","response":"the Nile","value":200,"isDailyDouble":false},{"clue":"80% of Washington, D.C.'s fresh drinking water comes from this river","response":"the Potomac","value":400,"isDailyDouble":false},{"clue":"Stratford & Warwick are important towns upon this river","response":"the Avon","value":600,"isDailyDouble":false},{"clue":"Mainz, Germany & Basel, Switzerland both lie on this river","response":"the Rhine","value":800,"isDailyDouble":false},{"clue":"During WWI 2 famous battles were fought near this river, the largest branch of the Seine","response":"the Marne","value":1000,"isDailyDouble":false}]},{"name":"BLACK AMERICA","clues":[{"clue":"Jackie Mabley, who had 3 children by age 14, used this appropriate stage name","response":"Moms (Mabley)","value":200,"isDailyDouble":false},{"clue":"G. Washington named Black surveyor B. Banneker to commission that laid out this city's boundaries","response":"Washington, D.C.","value":400,"isDailyDouble":false},{"clue":"It's said he also developed at least 75 products from the pecan","response":"George Washington Carver","value":600,"isDailyDouble":false},{"clue":"By order of Pres. Reagan, boxer Joe Louis was buried in this cemetery in 1981","response":"Arlington National Cemetery","value":800,"isDailyDouble":false},{"clue":"He grew up in Harlem & used it as setting for his 1st novel, \"Go Tell It on the Mountain\\\"","response":"James Baldwin","value":1000,"isDailyDouble":false}]}]