[{"name":"NICE SIDE WHISKERS!","clues":[{"clue":"Before becoming a prolific author, he taught biochemistry","response":"(Isaac) Asimov","value":400,"isDailyDouble":false},{"clue":"He was both the eighth vice-president and the eighth president","response":"Van Buren","value":800,"isDailyDouble":false},{"clue":"Here's this waltz king at around age 50","response":"(Johann) Strauss","value":1200,"isDailyDouble":false},{"clue":"Here's this general late in life, still sporting his signature side whiskers","response":"(Ambrose) Burnside","value":1600,"isDailyDouble":true},{"clue":"His long reign over Austria-Hungary ended with his death in 1916","response":"Franz Joseph","value":2000,"isDailyDouble":false}]},{"name":"U.S. AGENCIES","clues":[{"clue":"The Consumer Products Safety Commission has no authority over motor vehicles or this pair covered by the FDA","response":"food and drug","value":400,"isDailyDouble":false},{"clue":"In 1940 the Bureau of Fisheries & the Bureau of Biological Survey merged & became this","response":"Fish and Wildlife Service","value":800,"isDailyDouble":false},{"clue":"This Treasury agency began making postage stamps in 1894","response":"Bureau of Engraving and Printing","value":1200,"isDailyDouble":false},{"clue":"In 1981 this agency of volunteers who perform social services overseas became independent","response":"Peace Corps","value":1600,"isDailyDouble":false},{"clue":"Abbreviated USGS, its top priority is topography","response":"United States Geological Survey","value":2000,"isDailyDouble":false}]},{"name":"THANKS FOR THE MEMOIRS","clues":[{"clue":"In \"Dream Catcher\" Margaret A. Salinger writes about life with Dad, this reclusive author","response":"J.D. Salinger","value":400,"isDailyDouble":false},{"clue":"This cancer survivor tells of his \"Journey Back to Life\" in \"It's Not About the Bike\\\"","response":"Lance Armstrong","value":800,"isDailyDouble":true},{"clue":"Susanna Kaysen's 2-year stay at a psychiatric institute is recounted in this memoir","response":"Girl, Interrupted","value":1200,"isDailyDouble":false},{"clue":"This girl group singer penned the memoir \"Be My Baby\\\"","response":"Ronnie Spector","value":1600,"isDailyDouble":false},{"clue":"In \"Command Performance\", this actress discusses \"The Theater of Politics\" — namely, her 4-year term as head of the NEA","response":"Jane Alexander","value":2000,"isDailyDouble":false}]},{"name":"LANGUAGES","clues":[{"clue":"Maltese, which developed from a dialect of Arabic, is the only form of Arabic written in this alphabet","response":"the Latin alphabet (or Roman alphabet)","value":400,"isDailyDouble":false},{"clue":"(I'm Lara Logan of CBS News.) As a reporter I find it helpful to know many languages, so I speak English, French, Portuguese & this Germanic language of my homeland, South Africa","response":"Afrikaans","value":800,"isDailyDouble":false},{"clue":"Computer fonts are now available to writers of this most widely spoken Native American language in the United States","response":"Navajo","value":1200,"isDailyDouble":false},{"clue":"Mam is a Mayan language spoken in Mexico's Chiapas state & by around a half million in this country","response":"Guatemala","value":1600,"isDailyDouble":true},{"clue":"Enets, a Samoyedic language of Siberia, has 2 dialects: Forest Enets & this type named for a permafrost region","response":"Tundra","value":2000,"isDailyDouble":false}]},{"name":"CHARLIE CHAPLIN","clues":[{"clue":"This character was introduced in a 1914 short & Chaplin played him for 26 years","response":"the Little Tramp","value":400,"isDailyDouble":false},{"clue":"Chaplin's first film, \"Making a Living\", was made for this studio headed by Mack Sennett","response":"Keystone","value":800,"isDailyDouble":false},{"clue":"This 1921 film co-starring Jackie Coogan was the first feature written & directed by Chaplin","response":"The Kid","value":1200,"isDailyDouble":false},{"clue":"In 1919 Chaplin, Mary Pickford, D.W. Griffith & Douglas Fairbanks founded this film studio","response":"United Artists","value":1600,"isDailyDouble":false},{"clue":"Chaplin secretly wed this actress at sea in 1936; 6 years later their marriage was on the rocks","response":"Paulette Goddard","value":2000,"isDailyDouble":false}]},{"name":"FRENCH HISTORY","clues":[{"clue":"Not the beginning of a beautiful friendship, the Agadir Incident pitted Germany vs. France in this N. African country","response":"Morocco","value":400,"isDailyDouble":false},{"clue":"The law that made July 14 a holiday actually honored that date in this year, 1 year later than you might think","response":"1790","value":800,"isDailyDouble":false},{"clue":"A wartime adviser to de Gaulle, he was at the \"center\" of French politics as president from 1969 to 1974","response":"Pompidou","value":1200,"isDailyDouble":false},{"clue":"The French adapted the name of the Irinakhoiw into this & fought them in N. America for the second half of the 1600s","response":"the Iroquois","value":1600,"isDailyDouble":false},{"clue":"In 1137 Louis VII married this woman whose huge dowry was the subject of contention for centuries","response":"Eleanor of Aquitaine","value":2000,"isDailyDouble":false}]},{"name":"FRENCH AUTHORS","clues":[{"clue":"His 1st novelette, published in 1863, was \"5 Weeks in a Balloon\\\"","response":"Jules Verne","value":400,"isDailyDouble":false},{"clue":"This existential philosopher was a distant cousin of Albert Schweitzer","response":"(Jean-Paul) Sartre","value":800,"isDailyDouble":false},{"clue":"This \"Candide\" author so inveighed against the church, they denied him a Christian burial","response":"Voltaire","value":1200,"isDailyDouble":false},{"clue":"Louise Colet's novel \"Lui\" was a scandalous account of her affair with this \"Madame Bovary\" author","response":"(Gustave) Flaubert","value":1600,"isDailyDouble":false},{"clue":"He was a Franciscan monk before he wrote the racy \"Gargantua & Pantagruel\\\"","response":"François Rabelais","value":2000,"isDailyDouble":false}]},{"name":"THE U.N.","clues":[{"clue":"It's the \"Principal judicial organ of the United Nations\\\"","response":"World Court/International Court of Justice","value":400,"isDailyDouble":false},{"clue":"The seventh Secretary-General, he's fluent in English, French & several African languages","response":"Kofi Annan","value":800,"isDailyDouble":false},{"clue":"United Nations troops first arrived to keep the peace on this eastern Mediterranean isle in March 1964","response":"Cyprus","value":1200,"isDailyDouble":false},{"clue":"Born in 1918, this controversial figure served in World War II & was the fourth Secretary-General of the United Nations","response":"Kurt Waldheim","value":1600,"isDailyDouble":false},{"clue":"In 1992 this troubled European nation was expelled from the United Nations","response":"Yugoslavia","value":2000,"isDailyDouble":false}]},{"name":"DANCE COMPANIES","clues":[{"clue":"Women auditioning for this leggy New York City dance troupe must between 5'6\" & 5'10 1/2\" in height","response":"the Rockettes","value":400,"isDailyDouble":false},{"clue":"In 1992 Joaquin Cortes formed his own company that featured this gypsy dance","response":"flamenco","value":800,"isDailyDouble":false},{"clue":"The building housing this dance company opened August 20, 1856, in time for Czar Alexander II's coronation","response":"the Bolshoi","value":1200,"isDailyDouble":false},{"clue":"This company's present artistic director is, fittingly, Kevin McKenzie from the good old United States","response":"the American Ballet Theater","value":1600,"isDailyDouble":false},{"clue":"During foreign tours, the Mariinsky Ballet Company is known by this name","response":"the Kirov","value":2000,"isDailyDouble":true}]},{"name":"DRIVING","clues":[{"clue":"Cruising around Phoenix—that driver must be awfully short—oh, it's Waymo, Google's version of these","response":"self-driving cars","value":400,"isDailyDouble":false},{"clue":"To make driving safer, all new cars sold in the U.S. since 1998 require driver & front passenger ones","response":"air bags","value":800,"isDailyDouble":false},{"clue":"To save wear & tear on my car's gearbox, lately I've been using the \"double clutch\" technique to do this","response":"shift gears","value":1200,"isDailyDouble":false},{"clue":"You're in charge of the road maps; we're using ones from this 2-name company that made its first ones in 1904","response":"Rand-McNally","value":1600,"isDailyDouble":false},{"clue":"For long trips, I'm glad our car has OBD, on-board these to let us know when something goes wrong","response":"on-board diagnostics","value":2000,"isDailyDouble":false}]},{"name":"WHO MAKES THAT?","clues":[{"clue":"The $215 LeBron 9 Limited iD shoe","response":"Nike","value":400,"isDailyDouble":false},{"clue":"The Mach3 razor","response":"Gillette","value":800,"isDailyDouble":false},{"clue":"The Escalade hybrid","response":"Cadillac","value":1200,"isDailyDouble":false},{"clue":"The official Major League baseball, & lots of gloves, too","response":"Rawlings","value":1600,"isDailyDouble":false},{"clue":"A box of 24 medium soft lead No. 2s, \"the world's best pencil\\\"","response":"(Dixon) Ticonderoga","value":2000,"isDailyDouble":false}]},{"name":"OCEANIA","clues":[{"clue":"(Jimmy of the Clue Crew shows us a map of part of the South Pacific.) Two of the southernmost islands in Oceania are Chatham Island & Campbell Island, today both part of this country","response":"New Zealand","value":400,"isDailyDouble":false},{"clue":"Its .tv Internet domain has been a source of income for this Pacific island country","response":"Tuvalu","value":800,"isDailyDouble":false},{"clue":"(Kelly of the Clue Crew shows us a map of part of the South Pacific.) Port Moresby, on the Coral Sea, is the capital of this three-named country","response":"Papua New Guinea","value":1200,"isDailyDouble":false},{"clue":"If you want to see this country's king & family, attend Centenary Church in Nuku'alofa on Sundays","response":"Tonga","value":1600,"isDailyDouble":false},{"clue":"(Jimmy of the Clue Crew shows us a map of part of South America and the Pacific Ocean.) In 1766 Philip Carteret & Samuel Wallis sailed from England in two ships; storms separated them, & while Carteret discovered Pitcairn, Wallis found this other island that's part of the H.M.S. Bounty story","response":"Tahiti","value":2000,"isDailyDouble":false}]},{"name":"WORLD GEOGRAPHY","clues":[{"clue":"More than 80% of Algeria is covered by this desert","response":"Sahara","value":400,"isDailyDouble":false},{"clue":"Gwynedd & Clwyd are the northernmost counties in this country, part of the United Kingdom","response":"Wales","value":800,"isDailyDouble":false},{"clue":"Part of this South American country's city of La Paz lies in a canyon carved by the La Paz River","response":"Bolivia","value":1200,"isDailyDouble":false},{"clue":"This city became the capital of the Saud dynasty in the early 1800s","response":"Riyadh","value":1600,"isDailyDouble":false},{"clue":"Bordered by Syria & Israel, this small country is only 135 miles long & 35 miles wide","response":"Lebanon","value":2000,"isDailyDouble":true}]},{"name":"WORLD LANDMARKS","clues":[{"clue":"Worshippers at this Jerusalem holy site insert bits of paper containing written prayers into its cracks","response":"the Wailing Wall","value":400,"isDailyDouble":false},{"clue":"Around 1400 B.C. Thutmose IV ordered a team to dig out the buried front paws of this landmark","response":"the Sphinx","value":800,"isDailyDouble":false},{"clue":"The pediment of his memorial contains a sculpture of the 5 members of the Declaration of Independence Drafting Committee","response":"Jefferson","value":1200,"isDailyDouble":false},{"clue":"Sainte-Chappelle, with fabulous stained glass windows, stands near the more famous Notre-Dame Cathedral on this island","response":"the Île de la Cité (in Paris)","value":1600,"isDailyDouble":false},{"clue":"The El Caracol structure at the ruins of this ancient Mayan city in Mexico served as a 10th century observatory","response":"Chichen Itza","value":2000,"isDailyDouble":true}]},{"name":"LET'S HAVE SOME CHILE","clues":[{"clue":"Just as in San Francisco, these are used in the port of Valparaiso to carry passengers up steep hillsides","response":"cable cars","value":400,"isDailyDouble":false},{"clue":"Chile's coat of arms features an Andean deer & this vulture that has a 10-foot wingspan","response":"a condor","value":800,"isDailyDouble":false},{"clue":"Chile's southernmost point, it lies on an island in the Tierra Del Fuego Archipelago","response":"Cape Horn","value":1200,"isDailyDouble":false},{"clue":"In 1973 he led a military junta that overthrew Salvador Allende, & then governed Chile for the next 16 years","response":"Augusto Pinochet","value":1600,"isDailyDouble":false},{"clue":"Chile's longest river, the Loa, flows through this arid & forbidding desert","response":"the Atacama","value":2000,"isDailyDouble":false}]},{"name":"RODS & COHNS","clues":[{"clue":"Maggie May know that in 2016 this rocker was knighted for his services to music & charity","response":"Rod Stewart","value":400,"isDailyDouble":false},{"clue":"Marc Cohn mentions W.C. Handy & \"the ghost of Elvis\" in his song \"Walking In\" this city","response":"Memphis","value":800,"isDailyDouble":false},{"clue":"Here's this man from Queensland in his prime in the 1960s","response":"Rod Laver","value":1200,"isDailyDouble":false},{"clue":"He told TV viewers that science fiction is \"the improbable made possible; fantasy, the impossible made probable\\\"","response":"Rod Serling","value":1600,"isDailyDouble":false},{"clue":"This onetime communist-hunting lawyer is a malevolent presence in \"Angels in America\\\"","response":"Roy Cohn","value":2000,"isDailyDouble":false}]},{"name":"\\\"W\"RITERS","clues":[{"clue":"His first published book was a biology text; his first novel was \"The Time Machine\\\"","response":"(H. G.) Wells","value":400,"isDailyDouble":false},{"clue":"\\\"Lady Windermere's Fan\", a comedy of manners, is by this Irish wit","response":"Oscar Wilde","value":800,"isDailyDouble":false},{"clue":"This playwright hit a homer with \"Fences\", which won him a Pulitzer","response":"(August) Wilson","value":1200,"isDailyDouble":false},{"clue":"Jonathan Franzen eulogized this 3-named author as having \"produced a thousand pages of world-class jest\\\"","response":"David Foster Wallace","value":1600,"isDailyDouble":false},{"clue":"Her first collection of stories, \"In Love and Trouble: Stories of Black Women\", was released in 1973","response":"(Alice) Walker","value":2000,"isDailyDouble":false}]},{"name":"MUSICAL INSTRUMENTS","clues":[{"clue":"Adolphe Sax invented the saxhorn, but he's more famous for inventing this","response":"saxophone","value":400,"isDailyDouble":false},{"clue":"A device that muffles the sound of an instrument or reduces its volume is called this","response":"mute","value":800,"isDailyDouble":false},{"clue":"This instrument's full name begins with \"violin\\\"","response":"cello","value":1200,"isDailyDouble":false},{"clue":"The \"fipple\" type of this instrument is blown like a whistle","response":"flute","value":1600,"isDailyDouble":false},{"clue":"Some of these extremely long instruments are twice as long as the Swiss herdsmen who blow them","response":"Alp horns","value":2000,"isDailyDouble":false}]},{"name":"WORLD HISTORY","clues":[{"clue":"President of Egypt during 1973 Yom Kippur War","response":"Anwar Sadat","value":400,"isDailyDouble":false},{"clue":"Last name of father & 2 sons who ruled Nicaragua between 1937 & 1979","response":"Somoza","value":800,"isDailyDouble":false},{"clue":"Some claim for 9 days in 1553, at age 15, Lady Jane Grey was this","response":"Queen of England","value":1200,"isDailyDouble":false},{"clue":"1 of 2 Chinese leaders married to the famous Soong sisters","response":"Chiang Kai-shek (or Sun Yat-sen)","value":1600,"isDailyDouble":true},{"clue":"In 1962, Ne Win overthrew U Nu to become this country's prime minister once more","response":"Burma","value":2000,"isDailyDouble":false}]},{"name":"ANTARCTIC WILDLIFE","clues":[{"clue":"(Sarah of the Clue Crew floats near a floe in Antarctica.) This seal here—the only type that eats warm-blooded animals—is named after a big cat due to the dark spots on its coat","response":"the leopard seal","value":400,"isDailyDouble":false},{"clue":"(Sarah of the Clue Crew goes hunting for killer whales in Antarctica.) One of the most spectacular features of the male orca, or killer whale, is this stabilizing fin; from the Latin for \"of the back\", it can be 6 feet in height","response":"the dorsal fin","value":800,"isDailyDouble":false},{"clue":"(Lisa Trotter reports from Antarctica.) Frigid Antarctic water is full of dissolved oxygen; it circulates through ice fish so they don't need this oxygen-carrying pigment, making them nearly colorless","response":"hemoglobin","value":1200,"isDailyDouble":false},{"clue":"(Sarah of the Clue Crew reports from Antarctica.) The Antarctic is home to several species of petrels, named perhaps because their habit of flying close to the water's surface is reminiscent of this apostle, who tried to walk on water with Jesus","response":"Peter","value":1600,"isDailyDouble":true},{"clue":"(Tom Ritchie reports from Antarctica.) The stubby bill & white eye ring are ways to recognize this penguin species that French explorer Jules Dumont d'Urville named after his wife","response":"the Adelie penguin","value":2000,"isDailyDouble":false}]},{"name":"FOLK MUSIC","clues":[{"clue":"Yarrow, Stookey, & Travers","response":"Pater, Paul & Mary","value":400,"isDailyDouble":false},{"clue":"This famous Stephen Foster song was originally published as \"Gwine to Run All Night\\\"","response":"\\\"Camptown Races\\\"","value":800,"isDailyDouble":false},{"clue":"His \"Funny Way of Laughin'\" got him a Grammy in 1962","response":"Burl Ives","value":1200,"isDailyDouble":false},{"clue":"In 1974, she was \"a free man in Paris\\\"","response":"Joni Mitchell","value":1600,"isDailyDouble":false},{"clue":"River mentioned in the following folk chantey: \"Oh, Shenandoah, / I love your daughter / Away, you rolling river\\\"","response":"Missouri","value":2000,"isDailyDouble":true}]},{"name":"HISTORIC SHIPS","clues":[{"clue":"Launched in 1959, the Savannah was the first American merchant ship powered by this","response":"nuclear energy","value":400,"isDailyDouble":false},{"clue":"(Jimmy of the Clue Crew shows a map on a monitor.) Separated by a storm near the Azores, two ships that were part of a famous trio both made it back to Spain in March, 1493 but without this flag ship that was wrecked on a wreath near Hispañola","response":"the Santa Maria","value":800,"isDailyDouble":false},{"clue":"Once the flagship of the USA's Pacific Squadron, it was salvaged by the Confederates & recommissioned as the Virginia","response":"the Merrimack","value":1200,"isDailyDouble":false},{"clue":"Jacques Cousteau converted a British minesweeper into this oceanographic research ship","response":"the Calypso","value":1600,"isDailyDouble":false},{"clue":"The last luxury liner to sink on a transatlantic voyage was this Italian vessel on July 25, 1956","response":"the Andrea Doria","value":2000,"isDailyDouble":false}]},{"name":"MY TV DADS","clues":[{"clue":"James Gandolfini led 2 types of families, each with their own unique sets of problems, on this HBO drama","response":"The Sopranos","value":400,"isDailyDouble":false},{"clue":"In \"Two and a Half Men\", he was just Duckie playing Alan Harper, dad to the half-man","response":"(Jon) Cryer","value":800,"isDailyDouble":false},{"clue":"On this show, Will moved in with his Auntie Viv & Uncle Phil, parents to Hilary, Ashley, Nicky & dance master Carlton","response":"The Fresh Prince of Bel-Air","value":1200,"isDailyDouble":false},{"clue":"Taiwanese immigrant Louis Huang makes a go of it in 1990s Orlando with his wife & 3 sons on this ABC sitcom","response":"Fresh Off the Boat","value":1600,"isDailyDouble":false},{"clue":"His 2017 Emmy award as dad & son on \"This Is Us\" was his second in two years—for your information, the \"K\" is for Kelby","response":"(Sterling K.) Brown","value":2000,"isDailyDouble":false}]},{"name":"AROUND THE BODY","clues":[{"clue":"(Kelly of the Clue Crew demonstrates what she is describing in the clue.) If you close your eyes, place your finger lightly on your eyelid, & move your eye, you'll feel the bulge of this, the outer layer of the eye","response":"the cornea","value":400,"isDailyDouble":false},{"clue":"The system inside these organs is commonly called the \"bronchial tree\\\"","response":"the lungs","value":800,"isDailyDouble":false},{"clue":"Skeletal muscle is also called striated muscle; another muscle type does not appear striated, giving it this name","response":"smooth muscle","value":1200,"isDailyDouble":false},{"clue":"The hip is this type of joint that allows rotary motion","response":"a ball & socket joint","value":1600,"isDailyDouble":false},{"clue":"(Jimmy of the Clue Crew shows an animation on the monitor.) When an injury like a cut is sustained, these blood cells change shape, become sticky, build up on the wound & form a plug","response":"platelets","value":2000,"isDailyDouble":true}]},{"name":"MUSICAL INSTRUMENTS","clues":[{"clue":"It's the smallest form of the grand piano, but it usually isn't played by infants","response":"the baby grand","value":400,"isDailyDouble":false},{"clue":"If you were a viola, you'd have this many strings","response":"four","value":800,"isDailyDouble":false},{"clue":"The trumpet, the trombone & the tuba are found in this section of the orchestra","response":"the brass section","value":1200,"isDailyDouble":false},{"clue":"Les Paul, recording pioneer & master of this instrument, doesn't read music","response":"the electric guitar","value":1600,"isDailyDouble":true},{"clue":"Typically, these Latin American rattles contain seeds or beads, but some modern ones are filled with lead shot","response":"maracas","value":2000,"isDailyDouble":false}]},{"name":"SPORTS","clues":[{"clue":"In 2008 Kelvin Sampson found he could no longer phone it in as hoops coach of this \"Hoosier\" school","response":"Indiana","value":400,"isDailyDouble":false},{"clue":"The Olympic triathlon consists of a 1.5 kilometer this, a 40-kilometer bike ride & a 10-kilometer run","response":"a swim","value":800,"isDailyDouble":false},{"clue":"In '08 ex-Ram Willie Gary sued this team for $100 mil. for videotaping his team's 2002 pre-Super Bowl practice","response":"the Patriots","value":1200,"isDailyDouble":false},{"clue":"This other name for Grand Prix racing refers to the specifications of the Federation Internationale de l'Automobile","response":"Formula One","value":1600,"isDailyDouble":true},{"clue":"In 2000 an expansion team known as the Minnesota Wild joined this professional sports league","response":"the National Hockey League (NHL)","value":2000,"isDailyDouble":false}]},{"name":"CANADIAN PROVINCIAL SYMBOLS","clues":[{"clue":"If I told you this province's flower was the dogwood, could you guess it? How about if it's the Pacific dogwood?","response":"British Columbia","value":400,"isDailyDouble":false},{"clue":"Quebec's motto is \"Je me souviens\", \"I\" do this","response":"I remember","value":800,"isDailyDouble":false},{"clue":"You can't sweep the category unless you know that this is the provincial sport of Saskatchewan","response":"curling","value":1200,"isDailyDouble":false},{"clue":"Of course this province's flag is basically the cross of St. Andrew with reverse colors","response":"Nova Scotia","value":1600,"isDailyDouble":true},{"clue":"Alberta picked the lodgepole this as its provincial tree, as it supplied ties for the railroad","response":"pine","value":2000,"isDailyDouble":false}]},{"name":"FELINES IN FICTION","clues":[{"clue":"This disappearing cat is owned by the Duchess of Wonderland","response":"the Cheshire Cat","value":400,"isDailyDouble":false},{"clue":"Tom Kitten gets rolled up in dough & is almost baked in a pudding in \"The Tale of Samuel Whiskers\" by this author","response":"Beatrix Potter","value":800,"isDailyDouble":false},{"clue":"In \"The House at Pooh Corner\", Rabbit & Piglet hatch a plot to unbounce this feline character","response":"Tigger","value":1200,"isDailyDouble":false},{"clue":"Mungojerrie & Bustopher Jones are memorable characters in this T.S. Eliot work","response":"Old Possum's Book of Practical Cats","value":1600,"isDailyDouble":false},{"clue":"Pixel the cat shows up in the Robert Heinlein work \"The Cat Who\" does this, which regular cats can't do","response":"Walks Through Walls","value":2000,"isDailyDouble":false}]},{"name":"AMERICAN INDIANS","clues":[{"clue":"It's said expression \"on the warpath\" isn't from Indians, but from this 1826 J.F. Cooper novel","response":"The Last of the Mohicans","value":400,"isDailyDouble":false},{"clue":"The Choctaw used to do this to their babies' heads","response":"bind them","value":800,"isDailyDouble":false},{"clue":"Memphis, Tenn.'s baseball team, the Chicks, is not named for poultry but for this Indian tribe","response":"Chickasaws","value":1200,"isDailyDouble":false},{"clue":"Tho to them it is an age-old religious symbol, since WWII the Navajo have limited its use","response":"swastika","value":1600,"isDailyDouble":false},{"clue":"Called \"Big Chief\" & proud of his Indian ancestry, Charles Curtis held this office from 1929-33","response":"Vice President of the United States","value":2000,"isDailyDouble":true}]},{"name":"THAT'S OLD STUFF","clues":[{"clue":"The British Museum displays an iron one of these with a gilded bronze scabbard from the Roman emperor Tiberius","response":"a sword","value":400,"isDailyDouble":false},{"clue":"Crystallized some 4.4 billion years ago, zircons found in Australia are the Earth's oldest known of these rock constituents","response":"minerals","value":800,"isDailyDouble":false},{"clue":"Since the 8th century, a 230-foot-tall statue of this man has loomed over China's Sichuan Province","response":"Buddha","value":1200,"isDailyDouble":false},{"clue":"Homo naledi, a 2-million-year-old discovery announced in 2015, is notable for a long, powerful this digit","response":"thumb","value":1600,"isDailyDouble":false},{"clue":"Mad King Ludwig began construction of this fairy-tale castle in 1869","response":"Neuschwanstein","value":2000,"isDailyDouble":false}]},{"name":"HORS D'OEUVRES","clues":[{"clue":"From Latin for \"undigested food\", crudites refers to these","response":"raw vegetables","value":400,"isDailyDouble":false},{"clue":"Chicken livers & water chestnuts wrapped in bacon; fortune cookies to follow","response":"rumaki","value":800,"isDailyDouble":false},{"clue":"Ideally, this type of small appetizer served on toast or crackers should be small enough to eat in 1 bite","response":"canapé","value":1200,"isDailyDouble":false},{"clue":"This chic Middle-Eastern dip is made primarily from chickpeas & served with pita bread","response":"hummus","value":1600,"isDailyDouble":false},{"clue":"Hors d'oeuvres is French for \"outside of\" this, which is usually when they're served","response":"work","value":2000,"isDailyDouble":false}]},{"name":"ABBREVIATED PROVERBS","clues":[{"clue":"\\\"Dead men T. N. T.\\\"","response":"tell no tales","value":400,"isDailyDouble":false},{"clue":"\\\"Many hands M. L. W.\\\"","response":"make light work","value":800,"isDailyDouble":false},{"clue":"\\\"Strike W. T. I. I. H.\\\"","response":"while the iron is hot","value":1200,"isDailyDouble":false},{"clue":"\\\"Beggars C. B. C.\\\"","response":"can't be choosers","value":1600,"isDailyDouble":false},{"clue":"\\\"The eyes are the W. O. T. S.\\\"","response":"windows of the soul","value":2000,"isDailyDouble":true}]},{"name":"\\\"M\"ISCELLANY","clues":[{"clue":"Add \"steen\" to the name of this tropical fruit & you get the name of another tropical fruit","response":"mango","value":400,"isDailyDouble":false},{"clue":"The aptly named Samantha Bond played this personal assistant in the films \"GoldenEye\" & \"Die Another Day\\\"","response":"Miss Moneypenny","value":800,"isDailyDouble":false},{"clue":"This landlocked country is bordered by Ukraine & Romania","response":"Moldova","value":1200,"isDailyDouble":false},{"clue":"The state mushroom of Minnesota & a relative of the truffle, this variety has a smoky, nutty flavor","response":"the morel","value":1600,"isDailyDouble":false},{"clue":"The name of this swift & dangerous current in the Arctic Ocean has come to be used for a large, fatal whirlpool","response":"a maelstrom","value":2000,"isDailyDouble":false}]},{"name":"IT'S A \"LOCK\\\"","clues":[{"clue":"Tetanus' nickname","response":"lockjaw","value":400,"isDailyDouble":false},{"clue":"You might hide a tuft of your sweetheart's hair in this small pendant","response":"locket","value":800,"isDailyDouble":false},{"clue":"She replaced Cloris Leachman as the mother figure on \"Lassie\\\"","response":"June Lockhart","value":1200,"isDailyDouble":false},{"clue":"One of his most famous works was \"An Essay Concerning Human Understanding\\\"","response":"John Locke","value":1600,"isDailyDouble":false},{"clue":"\\\"In the spring a young man's fancy lightly turns to thoughts of love\" in this poetic \"Hall\\\"","response":"(Alfred Lord Tennyson's) \"Locksley Hall\\\"","value":2000,"isDailyDouble":false}]},{"name":"SCIENCE & NATURE","clues":[{"clue":"In the East Indies certain species of this reptile are called flying dragons because they can glide from tree to tree","response":"Lizards","value":400,"isDailyDouble":false},{"clue":"Newton, Cassegrain, Schmidt & Maksutov all have types of this instrument named for them","response":"Telescope","value":800,"isDailyDouble":false},{"clue":"The flexible neck of this bird of prey allows it to rotate its head an amazing 270 degrees","response":"Owl","value":1200,"isDailyDouble":true},{"clue":"Change 1 letter in \"protest\" to get this word for a protozoan & others in its kingdom","response":"Protist","value":1600,"isDailyDouble":false},{"clue":"Sir Humphry Davy named this yellowish-green gas from a Greek word meaning \"greenish-yellow\\\"","response":"Chlorine","value":2000,"isDailyDouble":false}]},{"name":"WOMEN","clues":[{"clue":"George Bush said in February 1989 that he calls her the \"Gray Fox\", not the \"Silver Fox\\\"","response":"Barbara Bush","value":400,"isDailyDouble":false},{"clue":"Dorothy Cudahy, called \"The First Lady of Irish radio\", was the 1st lady Grand Marshall of this NYC parade","response":"the St. Patrick's Day parade","value":800,"isDailyDouble":false},{"clue":"She left \"60 Minutes\" for an anchor job at ABC","response":"Diane Sawyer","value":1200,"isDailyDouble":false},{"clue":"18 years after Natalia Makarova's defection, she returned to dance with this Soviet ballet, not the Bolshoi","response":"the Kirov Ballet","value":1600,"isDailyDouble":true},{"clue":"\\\"Working for Love\" is the 1st novel by Tessa Dahl, daughter of Roald Dahl & this actress","response":"Patricia Neal","value":2000,"isDailyDouble":false}]},{"name":"ROMAN NAMES","clues":[{"clue":"In 27 B.C. Octavian was awarded this title meaning \"revered one\", & it became part of his name","response":"Augustus","value":400,"isDailyDouble":false},{"clue":"If Libertus were part of your name, you were previously one of these","response":"a slave","value":800,"isDailyDouble":true},{"clue":"The name of this rebel who died in 71 B.C honors a Greek city","response":"Spartacus","value":1200,"isDailyDouble":false},{"clue":"Publius Cornelius Scipio got the honorific Africanus due to his success in the second of these wars","response":"the Punic Wars","value":1600,"isDailyDouble":false},{"clue":"His surname meaning \"chickpea\", this orator had the image of one inscribed on a ceremonial plate in place of his name","response":"Cicero","value":2000,"isDailyDouble":false}]},{"name":"BEASTLY EXPRESSIONS","clues":[{"clue":"It precedes \"after while, crocodile\\\"","response":"see you later, alligator","value":400,"isDailyDouble":false},{"clue":"This term for an innocent person who takes the blame for others comes to us from Leviticus","response":"a scapegoat","value":800,"isDailyDouble":false},{"clue":"Ballplayers have used this 2-word phrase for a cramp or stiffness in an arm or leg muscle since the 1880s","response":"charley horse","value":1200,"isDailyDouble":false},{"clue":"(Sarah of the Clue Crew presents from Savannah, GA.) After meeting with black leaders here in Savannah, General Sherman issued an order giving land to black farmers, the likely origin of the promise \"40 acres and\" this","response":"a mule","value":1600,"isDailyDouble":false},{"clue":"In good spirits? Then you're probably this 4-word phrase \"at high tide\\\"","response":"happy as a clam","value":2000,"isDailyDouble":false}]},{"name":"PRESIDENTIAL ACQUISITIONS","clues":[{"clue":"The Louisiana Purchase","response":"Jefferson","value":400,"isDailyDouble":false},{"clue":"The Alaska Purchase","response":"Andrew Johnson","value":800,"isDailyDouble":true},{"clue":"Hawaii Annexation","response":"William McKinley","value":1200,"isDailyDouble":false},{"clue":"Florida Cession (OK, we'll tell you it was in 1819, during his first term)","response":"Monroe","value":1600,"isDailyDouble":false},{"clue":"Texas Annexation (late 1845)","response":"Polk","value":2000,"isDailyDouble":false}]},{"name":"THE ELEMENTS","clues":[{"clue":"Aristotle referred to it as \"liquid silver\\\"","response":"mercury","value":400,"isDailyDouble":false},{"clue":"This radioactive element was discovered in & named for the \"Golden State\\\"","response":"californium","value":800,"isDailyDouble":false},{"clue":"This pair discovered polonium; francium was discovered by someone else","response":"the Curies (Pierre & Marie)","value":1200,"isDailyDouble":false},{"clue":"In the universe, it's second only to hydrogen in abundance & lightness","response":"helium","value":1600,"isDailyDouble":false},{"clue":"The name of this noble gas is from a Greek word for \"hidden\\\"","response":"krypton","value":2000,"isDailyDouble":true}]},{"name":"RIVERS","clues":[{"clue":"The Snake joins this river just south of Pasco, Washington","response":"the Columbia","value":400,"isDailyDouble":false},{"clue":"Here's the famed Lorelei rock in this European river","response":"the Rhine","value":800,"isDailyDouble":false},{"clue":"The ancient city of Ur lay along this river that helped make the Fertile Crescent fertile","response":"the Euphrates","value":1200,"isDailyDouble":false},{"clue":"Meaning \"great river\", it rises out of a bog in Zambia","response":"the Zambezi","value":1600,"isDailyDouble":false},{"clue":"Whitehorse is on this river","response":"the Yukon","value":2000,"isDailyDouble":false}]},{"name":"EVERYTHING YOU ALWAYS WANTED TO KNOW ABOUT SEX","clues":[{"clue":"A fertilized egg embeds itself in the wall of this organ, also called the womb","response":"Uterus","value":400,"isDailyDouble":false},{"clue":"These pollen-bearing organs that include the anther are a plant's male flower parts","response":"Stamen","value":800,"isDailyDouble":false},{"clue":"This cell that is produced when a sperm fertilizes an egg measures 0.1 mm in diameter","response":"Zygote","value":1200,"isDailyDouble":false},{"clue":"Female sex hormones like estrogen may be called gynogens; male ones like testosterone are these","response":"Androgens","value":1600,"isDailyDouble":false},{"clue":"Also called reduction division, this type of nuclear division underlies all sexual reproduction","response":"Meiosis","value":2000,"isDailyDouble":false}]},{"name":"ART","clues":[{"clue":"The enigmatic smile in this circa 1503 painting has often been imitated but never duplicated","response":"the \"Mona Lisa\\\"","value":400,"isDailyDouble":false},{"clue":"Paul Cezanne was noted for this type of painting which often depicts a bowl or basket of fruit","response":"still life","value":800,"isDailyDouble":false},{"clue":"In 1857 this lithographer made his bookkeeper James Merritt Ives a partner","response":"(Nathaniel) Currier","value":1200,"isDailyDouble":false},{"clue":"Edgar Degas & Mary Cassatt used these soft crayons whose name is synonymous with pale colors","response":"pastels","value":1600,"isDailyDouble":false},{"clue":"\\\"Three Musicians\", a 1921 work by this Spaniard, is considered one of the greatest Cubist paintings","response":"(Pablo) Picasso","value":2000,"isDailyDouble":false}]},{"name":"CLIFFS NOTES: DRAMA","clues":[{"clue":"Willy: \"I'm tired.\" Howard: \"Oh yeah? You're fired\\\"","response":"Death of a Salesman","value":400,"isDailyDouble":false},{"clue":"Martha: \"I'm drunk.\" Nick: \"I'm confused.\" Honey: \"I'm mousy.\" George: \"I'm going to bed\\\"","response":"Who's Afraid of Virginia Woolf?","value":800,"isDailyDouble":false},{"clue":"Laura: \"You broke my unicorn!\" Gentleman Caller: \"whoops\\\"","response":"The Glass Menagerie","value":1200,"isDailyDouble":true},{"clue":"Act One, \"Daily Life\": Stage Manager: \"My God, is this place boring\\\"","response":"Our Town","value":1600,"isDailyDouble":false},{"clue":"Estragon: \"Is he here yet?\" Vladimir: \"Nope\" (curtain)","response":"Waiting for Godot","value":2000,"isDailyDouble":false}]},{"name":"EPIC POEMS AS COUNTRY SONGS","clues":[{"clue":"8th century: \"When you come home from the mead hall, you're gonna find yourself a dragon\\\"","response":"Beowulf","value":400,"isDailyDouble":false},{"clue":"800s B.C., maybe: \"I might be a long-lost husband, but that don't mean you get my wife\\\"","response":"the Odyssey","value":800,"isDailyDouble":false},{"clue":"Early 14th century: \"I was running 'round hell's circles till I saw your heavenly spheres\\\"","response":"Dante's Inferno (or Divine Comedy)","value":1200,"isDailyDouble":false},{"clue":"Around 20 B.C.: \"I left Troy behind me 'cause I had to be a Roman\\\"","response":"the Aeneid","value":1600,"isDailyDouble":false},{"clue":"11th century: \"If you're looking for a sure thing, baby, take a Chanson me\\\"","response":"The Song of Roland (La Chanson de Roland)","value":2000,"isDailyDouble":false}]},{"name":"GEOGRAPHIC SPELLING BEE","clues":[{"clue":"The name of this large sea comes from words for \"middle of the land\\\"","response":"M-E-D-I-T-E-R-R-A-N-E-A-N","value":400,"isDailyDouble":false},{"clue":"This 19,340-foot African peak is said to be the highest \"walkable\" mountain in the world","response":"K-I-L-I-M-A-N-J-A-R-O","value":800,"isDailyDouble":false},{"clue":"It's Paraguay's largest city","response":"A-S-U-N-C-I-O-N","value":1200,"isDailyDouble":false},{"clue":"The Dole Pineapple Company once owned 98% of this 5-letter Hawaiian island","response":"L-A-N-A-I","value":1600,"isDailyDouble":false},{"clue":"The dodo once made its home on this island about 500 miles east of Madagascar","response":"M-A-U-R-I-T-I-U-S","value":2000,"isDailyDouble":false}]},{"name":"STAGE NAME'S THE SAME","clues":[{"clue":"Funnyman director Melvin Kaminsky & funnyman director Albert Einstein","response":"Brooks","value":400,"isDailyDouble":false},{"clue":"\\'70s TV star John Sanford & \"Beat Shazam\" host Eric Bishop","response":"Foxx","value":800,"isDailyDouble":false},{"clue":"\\\"Mrs. Soffel\" Diane Hall & \"Mr. Mom\" Michael Douglas","response":"Keaton","value":1200,"isDailyDouble":false},{"clue":"Tall comedian Brad Gerstenfeld & '70s teen idol Leif Per Nervik","response":"Garrett","value":1600,"isDailyDouble":false},{"clue":"Screen legend Lucille LeSueur & Broadway legend Michael Dumbell-Smith","response":"Crawford","value":2000,"isDailyDouble":false}]},{"name":"SCIENCE VOCABULARY","clues":[{"clue":"From a word meaning \"insect\", it's the study of bugs","response":"entomology","value":400,"isDailyDouble":false},{"clue":"Atoms share a pair of electrons in this type of chemical bond","response":"covalent","value":800,"isDailyDouble":false},{"clue":"\\\"Specific\" this is the ratio of a substance's density to that of a standard substance, often water","response":"gravity","value":1200,"isDailyDouble":true},{"clue":"In physics, a body at rest is in \"static\" this if all the forces acting on it cancel each other out","response":"equilibrium","value":1600,"isDailyDouble":false},{"clue":"This slow wobbling of the Earth's axis of rotation completes a cycle every 26,000 years or so","response":"precession","value":2000,"isDailyDouble":false}]},{"name":"CONTINENTAL DRIFTING","clues":[{"clue":"Villarica & Cotopaxi are volcanoes found on this continent","response":"South America","value":400,"isDailyDouble":false},{"clue":"Of 20, 30 or 50%, the percentage of the Earth's land Asia occupies as the world's largest continent","response":"30%","value":800,"isDailyDouble":false},{"clue":"The equator stretches across more land mass on this continent than any other","response":"Africa","value":1200,"isDailyDouble":true},{"clue":"(Jon of the Clue Crew shows a globe of the geologically ancient world on the monitor.) Meaning \"all earth\", it's the term Alfred Wegener gave to an historic, theoretical supercontinent","response":"Pangaea","value":1600,"isDailyDouble":false},{"clue":"It's also the sixth-largest country in area","response":"Australia","value":2000,"isDailyDouble":false}]},{"name":"THE HUMAN BODY","clues":[{"clue":"2 skull cavities called the orbits house these organs","response":"the eyes","value":400,"isDailyDouble":false},{"clue":"A sphincter at the end of this tube allows swallowed food to enter the stomach","response":"the esophagus","value":800,"isDailyDouble":false},{"clue":"The pulmonary artery carries blood from the right ventricle of the heart to this organ pair","response":"the lungs","value":1200,"isDailyDouble":false},{"clue":"Much of the bile made by the liver is stored in this pear-shaped sack","response":"the gallbladder","value":1600,"isDailyDouble":false},{"clue":"From the Greek for snail shell, it's the spiral-shaped part of the inner ear","response":"the cochlea","value":2000,"isDailyDouble":true}]},{"name":"U.S. CITIES","clues":[{"clue":"Britannica calls this Georgia capital the artistic center of the Southeast","response":"Atlanta","value":400,"isDailyDouble":false},{"clue":"This largest Delaware city was founded by the Swedes who called it Fort Christina","response":"Wilmington","value":800,"isDailyDouble":false},{"clue":"Now a ghost town, in the 1870s this Nevada locale had a population of 30,000","response":"Virginia City","value":1200,"isDailyDouble":false},{"clue":"Texas city southeast of Dallas named for the 10th president of the United States","response":"Tyler","value":1600,"isDailyDouble":true},{"clue":"Alabama city on the Black Warrior River named for a Choctaw chief whose name meant \"black warrior\\\"","response":"Tuscaloosa","value":2000,"isDailyDouble":false}]},{"name":"ISLANDS","clues":[{"clue":"Newport is the largest city on this island for which the state is named","response":"Rhode Island","value":400,"isDailyDouble":false},{"clue":"In 1975, New York City's borough of Richmond was officially renamed this","response":"Staten Island","value":800,"isDailyDouble":false},{"clue":"This eastern Mediterranean island country is considered part of the Middle East","response":"Cyprus","value":1200,"isDailyDouble":false},{"clue":"This largest of Japan's four main islands is sometimes referred to as \"The Mainland\\\"","response":"Honshu","value":1600,"isDailyDouble":false},{"clue":"This island was a separate British dominion that did not join Canada until 1949","response":"Newfoundland","value":2000,"isDailyDouble":false}]},{"name":"\\\"W\"RITERS","clues":[{"clue":"He wrote a \"Textbook of Biology\" 2 years before \"The Time Machine\\\"","response":"H.G. Wells","value":400,"isDailyDouble":false},{"clue":"Raised on a farm, she didn't begin writing her \"Little House\" series until she was 65","response":"Laura Ingalls Wilder","value":800,"isDailyDouble":false},{"clue":"Service aboard a minesweeper in World War II gave this author the background he needed to write \"The Caine Mutiny\\\"","response":"Herman Wouk","value":1200,"isDailyDouble":false},{"clue":"From 1881 to 1885 this \"Ben-Hur\" author served as the USA's minister to Turkey","response":"Lew Wallace","value":1600,"isDailyDouble":false},{"clue":"The cherry tree story began with the 1806 edition of his \"The Life and Memorable Actions of George Washington\\\"","response":"Parson Weems","value":2000,"isDailyDouble":false}]},{"name":"ICE CREAM","clues":[{"clue":"In 1988 a 4 1/2-mile one of these fruity desserts was created in Pennsylvania","response":"Banana Split","value":400,"isDailyDouble":false},{"clue":"Minty Python & Choc Ness Monster were suggestions for this company's new British flavor","response":"Ben & Jerry's","value":800,"isDailyDouble":false},{"clue":"Mid-20th c. electric refigerators meant no more waiting for frozen treats until he cometh","response":"Iceman","value":1200,"isDailyDouble":false},{"clue":"This chain once boasted over 1,000 restaurants serving 28 flavors with 16% butterfat","response":"Howard Johnson's","value":1600,"isDailyDouble":false},{"clue":"In the 1980s restauranteur David Mintz began marketing soy ice cream under this brand name","response":"Tofutti","value":2000,"isDailyDouble":false}]},{"name":"MOUNTAINS","clues":[{"clue":"Lake Kawaguchi is famous for the inverted image of this mountain reflected in its waters","response":"Mt. Fuji","value":400,"isDailyDouble":false},{"clue":"This chain that runs from Newfoundland to Alabama was formed about 250 million years ago","response":"the Appalachians","value":800,"isDailyDouble":false},{"clue":"Uhuru Peak is the highest point of this dormant volcano, Africa's highest mountain","response":"Kilimanjaro","value":1200,"isDailyDouble":false},{"clue":"W.A. Dickey, a prospector, named the highest peak in North America this","response":"Mt. McKinley","value":1600,"isDailyDouble":false},{"clue":"Orizaba is the highest peak in this Mexican \"mother range\\\"","response":"the Sierra Madres","value":2000,"isDailyDouble":false}]},{"name":"\\\"OB\"-SESSIVE","clues":[{"clue":"A real-life event that illustrates a moral principle is this type of \"lesson\\\"","response":"an object lesson","value":400,"isDailyDouble":false},{"clue":"This word for a type of notice in a newspaper is from the Latin for \"death\\\"","response":"an obituary","value":800,"isDailyDouble":false},{"clue":"The front side of a coin","response":"the obverse","value":1200,"isDailyDouble":false},{"clue":"Type of training that'll bring your dog to heel (& sit & stay)","response":"obedience training","value":1600,"isDailyDouble":false},{"clue":"The Washington Monument is one","response":"an obelisk","value":2000,"isDailyDouble":false}]},{"name":"LADIES IN SPACE","clues":[{"clue":"In 1993, Kathryn Thornton went into space to help repair the flawed \"vision\" of this, which had mirror problems","response":"the Hubble","value":400,"isDailyDouble":false},{"clue":"In 1992 Mae Jemison became the first African-American woman astronaut, on this shuttle whose name means \"to try\\\"","response":"Endeavour","value":800,"isDailyDouble":false},{"clue":"In 1984 Kathryn Sullivan became the 1st U.S. woman to walk in space as this woman made her second shuttle trip","response":"Sally Ride","value":1200,"isDailyDouble":false},{"clue":"This first woman in space was named a hero of the Soviet Union & awarded the Order of Lenin","response":"(Valentina) Tereshkova","value":1600,"isDailyDouble":false},{"clue":"Clear & transparent last name of astronaut Shannon, an STS-58 member","response":"Lucid","value":2000,"isDailyDouble":true}]},{"name":"A BUNCH OF STUFF","clues":[{"clue":"According to USDA dietary guidelines, at least half of what you eat from this food group should be \"whole\\\"","response":"grains","value":400,"isDailyDouble":false},{"clue":"Another term for a pioneer, it's also a member of Portland's NBA team","response":"a trailblazer","value":800,"isDailyDouble":false},{"clue":"In 2012 this 1972 presidential candidate passed away at age 90 in South Dakota","response":"(George) McGovern","value":1200,"isDailyDouble":false},{"clue":"It's the 16-letter word for a 150th anniversary","response":"a sesquicentennial","value":1600,"isDailyDouble":false},{"clue":"This painter's \"The Garden of Earthly Delights\" is over 7 feet tall & over 12 feet long","response":"(Hieronymus) Bosch","value":2000,"isDailyDouble":false}]},{"name":"WORLD CITIES","clues":[{"clue":"Sacre-Coeur, Sacred heart Church, stands atop Montmartre, this capital's highest point","response":"Paris","value":400,"isDailyDouble":false},{"clue":"This capital city's Plaza de Espana contains a statue of Cervantes","response":"Madrid","value":800,"isDailyDouble":false},{"clue":"It took 14 years to build this Australian city's white-shelled opera house on Bennelong Point","response":"Sydney","value":1200,"isDailyDouble":false},{"clue":"This Italian city's Uffizi Palace was commissioned by Cosimo de Medici & begun in 1560","response":"Florence","value":1600,"isDailyDouble":false},{"clue":"The name of this Russian port on the Pacific means \"rule the east\\\"","response":"Vladivostok","value":2000,"isDailyDouble":false}]},{"name":"WORLD GEOGRAPHY","clues":[{"clue":"The African kingdom of Buganda was located in what's now this country","response":"Uganda","value":400,"isDailyDouble":false},{"clue":"A separate Turkish state was proclaimed on this Mediterranean island in 1975","response":"Cyprus","value":800,"isDailyDouble":false},{"clue":"The largest island surrounded by fresh water is Ilha de Marajo in this South American river","response":"Amazon","value":1200,"isDailyDouble":false},{"clue":"A statue of Roger Williams stands in a park overlooking this city Williams founded in 1636","response":"Providence","value":1600,"isDailyDouble":false},{"clue":"Gatun Lake & Miraflores Lake are part of this waterway","response":"Panama Canal","value":2000,"isDailyDouble":true}]},{"name":"SCIENCE","clues":[{"clue":"Genes on this sex chromosome control color vision, blood clotting & muscular dystrophy","response":"the X chromosome","value":400,"isDailyDouble":false},{"clue":"An amoeba of the Endamoeba genus lives in this kitchen insect pest","response":"the (cock)roach","value":800,"isDailyDouble":false},{"clue":"Honeybees get their sugar from nectar & their protein & fat from this","response":"pollen","value":1200,"isDailyDouble":false},{"clue":"The Moon has 2 main types of surfaces: highlands & these, both of which have craters","response":"maria (seas)","value":1600,"isDailyDouble":false},{"clue":"Gold & other precious metals are measured on this weight system that has 12 ounces to the pound","response":"troy","value":2000,"isDailyDouble":false}]},{"name":"WORLD LEADERS","clues":[{"clue":"Elizabeth II has seen 10 different prime ministers com & go, from this man to Tony Blair","response":"Winston Churchill","value":400,"isDailyDouble":false},{"clue":"Sir Muda Hassanal Bolkiah Mu'izzadin Waddaulah is the sultan of this country","response":"Brunei","value":800,"isDailyDouble":false},{"clue":"Helmut Kohl has passed this man's record as the longest-serving chancellor of post-WWII Germany","response":"(Konrad) Adenauer","value":1200,"isDailyDouble":false},{"clue":"(Hi, I'm Tracy Bingham.) When Mike Wallace interviewed this Iranian president in March 1997, the topic of \"Baywatch\" came up","response":"Hashemi Rafsanjani","value":1600,"isDailyDouble":true},{"clue":"This Peruvian president used to be a TV talk show host","response":"(Alberto) Fujimori","value":2000,"isDailyDouble":false}]},{"name":"A \"B\"6 SHOT","clues":[{"clue":"A narrative folk poem, or a simple, romantic song","response":"ballad","value":400,"isDailyDouble":false},{"clue":"A government reward, perhaps put \"on your head\\\"","response":"bounty","value":800,"isDailyDouble":false},{"clue":"It's the printed name of the author of an accompanying news story","response":"byline","value":1200,"isDailyDouble":false},{"clue":"It's the crime of having 2 wives at once","response":"bigamy","value":1600,"isDailyDouble":false},{"clue":"Job title of a college treasurer","response":"bursar","value":2000,"isDailyDouble":false}]},{"name":"MISH MASH","clues":[{"clue":"In 2017 ex-Portuguese PM António Guterres became the 9th man in this post with global responsibilities","response":"secretary-general of the UN","value":400,"isDailyDouble":false},{"clue":"In a song from \"The Music Man\", these \"led the big parade with a 110 cornets close at hand\\\"","response":"seventy-six trombones","value":800,"isDailyDouble":false},{"clue":"Named for a valley in Switzerland, this cheese is made with cow's milk","response":"Emmentaler","value":1200,"isDailyDouble":false},{"clue":"Harry Haller, the central figure in \"Steppenwolf\", has the same initials as his creator, this author","response":"(Hermann) Hesse","value":1600,"isDailyDouble":false},{"clue":"This Spaniard depicted rebellion in his country on the second & third of May in 1808","response":"Goya","value":2000,"isDailyDouble":false}]},{"name":"OLYMPIANS","clues":[{"clue":"Like his Roman counterpart Neptune, this Greek god is often depicted with his trident & a dolphin","response":"Poseidon","value":400,"isDailyDouble":false},{"clue":"This messenger god wore winged sandals called Talaria","response":"Hermes","value":800,"isDailyDouble":false},{"clue":"She was ready to go to battle from the moment she sprang from Zeus' head","response":"Athena","value":1200,"isDailyDouble":false},{"clue":"The Eleusinian Mysteries were secret religious rites honoring this Greek goddess of agriculture","response":"Demeter","value":1600,"isDailyDouble":false},{"clue":"As the wife of Zeus, she was the queen of the Olympian gods","response":"Hera","value":2000,"isDailyDouble":false}]},{"name":"THE WAR OF 1812","clues":[{"clue":"In this last battle of the War, about 2,000 British were killed, wounded or captured; fewer than 50 Americans were killed","response":"The Battle Of New Orleans","value":400,"isDailyDouble":false},{"clue":"On April 27, 1813 American forces captured York, the capital of upper Canada; today York is known by this name","response":"Toronto","value":800,"isDailyDouble":false},{"clue":"After the battle of Lake Erie, Congress gave this Naval hero a gold medal & $5,000, plus his share of prize money","response":"(Oliver Hazard) Perry","value":1200,"isDailyDouble":false},{"clue":"This Washington attorney was held prisoner aboard a British ship in mid-September 1814","response":"Francis Scott Key","value":1600,"isDailyDouble":true},{"clue":"In Article X of this treaty, both the U.S. & Britain agreed to \"use their best endeavours\" to abolish slavery","response":"the Treaty of Ghent","value":2000,"isDailyDouble":false}]},{"name":"AROUND THE GLOBE","clues":[{"clue":"In 1712, the capital of Russia was moved from Moscow to this port city; in 1918 after the Bolsheviks took power, it was moved back","response":"St. Petersburg","value":400,"isDailyDouble":false},{"clue":"Carlos Sanchez, a real coffee grower from Antioquia in this country, was an early portrayer of Juan Valdez","response":"Colombia","value":800,"isDailyDouble":false},{"clue":"The ECB, the European Central Bank, has its headquarters in this German city on the Main River","response":"Frankfurt","value":1200,"isDailyDouble":false},{"clue":"This ancient trade route linking China & the West stretched 4,000 miles from Xi'an in the east to the Mediterranean Sea","response":"the Silk Road","value":1600,"isDailyDouble":false},{"clue":"An attraction on this East African island a bit smaller than Maui is the house where Freddie Mercury lived as a child","response":"Zanzibar","value":2000,"isDailyDouble":false}]},{"name":"DEPT. OF THE INTERIOR","clues":[{"clue":"Liquid substance that's the Bureau of Reclamation's main concern","response":"Water","value":400,"isDailyDouble":false},{"clue":"Clinton thought this former Arizona governor superior; he made him Secretary of the Interior","response":"Bruce Babbitt","value":800,"isDailyDouble":false},{"clue":"In 1946 the Grazing Service was combined with another office to form the BLM, this","response":"Bureau of Land Management","value":1200,"isDailyDouble":false},{"clue":"This service runs Yellowstone & Yosemite","response":"National Park Service","value":1600,"isDailyDouble":false},{"clue":"Originally part of the Department of War, this bureau is concerned with the how & where of Native Americans","response":"Bureau of Indian Affairs","value":2000,"isDailyDouble":false}]},{"name":"BIOLOGY","clues":[{"clue":"Of all mammals, this one takes longest to mature","response":"Man (humans)","value":400,"isDailyDouble":false},{"clue":"The human body's largest bone","response":"Femur","value":800,"isDailyDouble":false},{"clue":"In 1956 scientists determined a normal human cell has this many chromosomes","response":"46","value":1200,"isDailyDouble":true},{"clue":"Light-sensitive layer of nerve tissue covering the back 2/3 of the eyeball, it's an extension of the brain","response":"Retina","value":1600,"isDailyDouble":false},{"clue":"This Swedish botanist, known for his system of classification, was the first to note that whales are mammals","response":"Carl Linnaeus","value":2000,"isDailyDouble":false}]},{"name":"EXPLORERS","clues":[{"clue":"In 1905 Roald Amundsen finally conquered this Atlantic-to-Pacific route explorers had sought for centuries","response":"the Northwest Passage","value":400,"isDailyDouble":false},{"clue":"John Speke accidentally shot himself before he was to debate Richard Burton over the source of this river","response":"the Nile","value":800,"isDailyDouble":false},{"clue":"A Royal Geographical Society expedition found him in 1873, dead; he'd been found in 1871 alive under more famous circumstances","response":"Livingstone","value":1200,"isDailyDouble":false},{"clue":"Scotsman Gordon Laing, the first European to reach this ancient African city, was murdered shortly after leaving there","response":"Timbuktu","value":1600,"isDailyDouble":false},{"clue":"The Ronne this 2-word feature is named for Edith Ronne, one of Antarctica's first female explorers","response":"ice shelf","value":2000,"isDailyDouble":false}]},{"name":"THE CITY'S TV SHOW","clues":[{"clue":"Episodes of this sitcom include \"The Gang Cracks the Liberty Bell\" & \"Frank Sets Sweet Dee on Fire\\\"","response":"It's Always Sunny in Philadelphia","value":400,"isDailyDouble":false},{"clue":"Lee Iacocca, G.Gordon Liddy & the Fat Boys guested on this 1980s Don Johnson superhip cop show","response":"Miami Vice","value":800,"isDailyDouble":false},{"clue":"As good cop Molly Solverson, Allison Tolman laid down the law in season 1 of this FX drama inspired by a movie","response":"Fargo","value":1200,"isDailyDouble":false},{"clue":"On this CBS spin-off in 2016, les bons temps stopped for a petty officer murdered during Mardi Gras","response":"NCIS: New Orleans","value":1600,"isDailyDouble":false},{"clue":"Partners came & went, but Dennis Franz stayed on the beat for the entirety of this show's 1993 to 2005 run","response":"NYPD Blue","value":2000,"isDailyDouble":false}]},{"name":"GILLIGAN'S \"I\"LAND","clues":[{"clue":"2 of its islands are Sicily & Sardinia","response":"Italy","value":400,"isDailyDouble":false},{"clue":"The North Atlantic Ocean holds this country, home to Europe's largest glacier","response":"Iceland","value":800,"isDailyDouble":false},{"clue":"The cathedral city of Cork is the second-largest city in this country","response":"Ireland","value":1200,"isDailyDouble":false},{"clue":"Fittingly, the national soccer team of this African nation is known as the Elephants","response":"the Ivory Coast","value":1600,"isDailyDouble":false},{"clue":"More than 17,500 islands, including Buru & Sulawesi, make up this equator-straddling country","response":"Indonesia","value":2000,"isDailyDouble":false}]},{"name":"POLISH HISTORY","clues":[{"clue":"In August 1939 Germany & this country secretly agreed to divide Poland","response":"the Soviet Union","value":400,"isDailyDouble":false},{"clue":"In 1957 Polish foreign minister Adam Rapacki proposed a European \"zone\" free of these","response":"nuclear weapons","value":800,"isDailyDouble":false},{"clue":"The Jagiellonian University in this city was Poland's nexus for Renaissance learning","response":"Krakow","value":1200,"isDailyDouble":false},{"clue":"In 1295 Przemysl II first used this crowned white bird on the coat of arms of the Kingdom of Poland","response":"the eagle","value":1600,"isDailyDouble":false},{"clue":"(Jimmy of the Clue Crew reports from Gdansk, Poland.) This labor union was formed here in Gdansk in 1980 & within months represented most Polish workers","response":"Solidarity","value":2000,"isDailyDouble":false}]},{"name":"\\\"PLAIN\" & \"SIMPLE\\\"","clues":[{"clue":"Charles Dickens' friend Charles Frederick Field was one of Scotland Yard's 1st of these, named for their nonuniform garb","response":"plainclothesman","value":400,"isDailyDouble":false},{"clue":"Going to the fair, this nursery rhyme guy meets a purveyor of baked goods","response":"Simple Simon","value":800,"isDailyDouble":false},{"clue":"As an acronym from around 1960, KISS stands for this instruction that includes an insult at no extra charge","response":"keep it simple, stupid","value":1200,"isDailyDouble":false},{"clue":"In the 18th century an explorer applied this 2-word term to a vast area of North America that isn't as flat as the name makes it sound","response":"the Great Plains","value":1600,"isDailyDouble":false},{"clue":"1888's these \"from the Hills\", Rudyard Kipling's first book of fiction, gives vivid portraits of life in British India","response":"Plain Tales","value":2000,"isDailyDouble":false}]},{"name":"ADD SOME CONSONANTS","clues":[{"clue":"Numbered explanatory comment at a page's bottom: OOOE","response":"a footnote","value":400,"isDailyDouble":false},{"clue":"MPH indicator: EEOEE","response":"speedometer","value":800,"isDailyDouble":false},{"clue":"A John Lennon classic: IAIE","response":"\\\"Imagine\\\"","value":1200,"isDailyDouble":false},{"clue":"A portable musical instrument: AOIO","response":"an accordion","value":1600,"isDailyDouble":false},{"clue":"Old MacDonald had this point in a planet's orbit when it's nearest to the Sun: EIEIO","response":"perihelion","value":2000,"isDailyDouble":false}]},{"name":"ATLAS CHAPS","clues":[{"clue":"Richard Bullington was project manager for the 9th & newest edition of this D.C. organization's renowned altas","response":"the National Geographic","value":400,"isDailyDouble":false},{"clue":"William, not Ayn, was the senior partner of this duo who started making maps in 1870s Chicago","response":"Rand McNally","value":800,"isDailyDouble":false},{"clue":"Arthur Norton's 1910 atlas of these charted more than 6,500 of them, some as faint as the 7th magnitude","response":"stars","value":1200,"isDailyDouble":false},{"clue":"It takes several people to move the nearly 6-foot-tall Klencke Atlas given to this king on his 1660 restoration","response":"Charles II","value":1600,"isDailyDouble":false},{"clue":"This 16th century cartographer wasn't projecting when he coined the term \"atlas\" to describe a large book of maps","response":"(Gerardus) Mercator","value":2000,"isDailyDouble":true}]},{"name":"WINES & SPIRITS","clues":[{"clue":"Krug & Tattinger are major producers of this sparkling French wine","response":"champagne","value":400,"isDailyDouble":false},{"clue":"New South Wales was this country's first wine-producing region","response":"Australia","value":800,"isDailyDouble":false},{"clue":"This whisky gets its smoky flavor when the malted barley is cured over burning peat","response":"Scotch","value":1200,"isDailyDouble":false},{"clue":"Calvados is a fine brandy made from this fruit, not from grapes","response":"apples","value":1600,"isDailyDouble":false},{"clue":"Some of this Norwegian \"water of life\" ts shipped to the Southern Hemisphere & back to mellow it","response":"akevitt","value":2000,"isDailyDouble":false}]},{"name":"RALLY TO THE CAUSE","clues":[{"clue":"It's to free this land invaded by China in 1950","response":"Tibet","value":400,"isDailyDouble":false},{"clue":"We're against this—a '60s slogan says it's \"not healthy for children & other living things\\\"","response":"war","value":800,"isDailyDouble":false},{"clue":"Bring candles—it's for TBTN, \"Take Back\" this","response":"the Night","value":1200,"isDailyDouble":false},{"clue":"It's organized by this lefty dot-org, motto \"Democracy in action\\\"","response":"MoveOn","value":1600,"isDailyDouble":false},{"clue":"It's to save equal Internet speed for all, aka \"net\" this","response":"neutrality","value":2000,"isDailyDouble":false}]},{"name":"EUROPEAN FOUNTAINS","clues":[{"clue":"It's said Alma von Goethe, the poet's granddaughter, was the model for the figure atop this city's Austria fountain","response":"Vienna","value":400,"isDailyDouble":false},{"clue":"A feature of Copenhagen's Tivoli Gardens is the fountain with bubbling tubes, codesigned by this physicist","response":"(Niels) Bohr","value":800,"isDailyDouble":false},{"clue":"The Eros statue in the Shaftesbury Memorial Fountain in this London \"Circus\" was one of the first to be made of aluminum","response":"Piccadilly Circus","value":1200,"isDailyDouble":false},{"clue":"A fountain in Paris near Pompidou Centre honors this composer with mechanical figures inspired by \"The Rite of Spring\\\"","response":"(Igor) Stravinsky","value":1600,"isDailyDouble":false},{"clue":"Designed by Nicola Salvi in 1732 & completed 30 years later, it's been called the most famous Baroque fountain in Rome","response":"the Trevi Fountain","value":2000,"isDailyDouble":false}]},{"name":"SAY THANK YOU!","clues":[{"clue":"In Spanish","response":"gracias","value":400,"isDailyDouble":false},{"clue":"In German","response":"danke","value":800,"isDailyDouble":false},{"clue":"In French","response":"merci","value":1200,"isDailyDouble":false},{"clue":"In Japanese","response":"domo arigato","value":1600,"isDailyDouble":false},{"clue":"In Russian","response":"spasiba","value":2000,"isDailyDouble":false}]},{"name":"SOLVE THE MYSTERY TITLE","clues":[{"clue":"An Easy Rawlins mystery: \"___ in a Blue Dress\\\"","response":"Devil","value":400,"isDailyDouble":false},{"clue":"Umberto Eco's \"The Name of the ___\\\"","response":"Rose","value":800,"isDailyDouble":false},{"clue":"Scott Turow's second novel \"The Burden of ___\\\"","response":"Proof","value":1200,"isDailyDouble":false},{"clue":"Dennis Lehane's \"___ River\\\"","response":"Mystic","value":1600,"isDailyDouble":false},{"clue":"By Edgar Allan Poe, \"The Mystery of ___ Roget\\\"","response":"Marie","value":2000,"isDailyDouble":false}]},{"name":"POETRY","clues":[{"clue":"\\\"I was chokin' mad w/thirst, an' the man that spied me 1st was our good old grinnin' gruntin' Gunga Din.\" he wrote","response":"Rudyard Kipling","value":400,"isDailyDouble":false},{"clue":"This author of \"Elegy Written In A Country Churchyard\" refused an offer to be poet laureate","response":"Thomas Gray","value":800,"isDailyDouble":false},{"clue":"The last line of her poem \"The New Colossus\" is \"I lift my lamp beside the golden door\\\"","response":"Emma Lazarus","value":1200,"isDailyDouble":false},{"clue":"He called \"The Chambered Nautilus\" \"The Ship of Pearl\\\"","response":"Oliver Wendell Holmes","value":1600,"isDailyDouble":false},{"clue":"\\\"Queen Mab\", \"Ozymandias\" & \"To A Skylark\" are 3 of the poems written by this Englishman","response":"Percy Bysshe Shelley","value":2000,"isDailyDouble":true}]},{"name":"BOTANY","clues":[{"clue":"This term refers to trees that shed all of their leaves each year, usually in the fall","response":"deciduous","value":400,"isDailyDouble":false},{"clue":"Around 1775 chemist Joseph Priestley showed that plants produce this gas","response":"oxygen","value":800,"isDailyDouble":false},{"clue":"The milkweed is the only plant on which these regal butterflies will lay their eggs","response":"a monarch butterfly","value":1200,"isDailyDouble":false},{"clue":"This largest U.S. cactus is sometimes pollinated by bats","response":"the saguaro","value":1600,"isDailyDouble":false},{"clue":"Plants absorb water from the soil through their roots by this process","response":"osmosis","value":2000,"isDailyDouble":true}]},{"name":"\\\"ODD\"s & \"END\"s","clues":[{"clue":"A section at the end of a book, or a vestigial body part","response":"an appendix","value":400,"isDailyDouble":false},{"clue":"To \"make\" these means to correct a past wrong","response":"amends","value":800,"isDailyDouble":false},{"clue":"A popular vote held to decide a single issue","response":"a referendum","value":1200,"isDailyDouble":false},{"clue":"Absolutely soaked with water","response":"sodden","value":1600,"isDailyDouble":false},{"clue":"Hay or straw given to livestock","response":"fodder","value":2000,"isDailyDouble":false}]},{"name":"BLESS YOU","clues":[{"clue":"One form of this pre-meal prayer begins, \"Bless us, O Lord, and these thy gifts\\\"","response":"grace","value":400,"isDailyDouble":false},{"clue":"He wore his brother Esau's clothes to finagle his father Isaac's blessing","response":"Jacob","value":800,"isDailyDouble":false},{"clue":"Term for Jesus' 8 statements beginning with \"Blessed are the poor in spirit...\\\"","response":"the Beatitudes","value":1200,"isDailyDouble":false},{"clue":"\\\"May His great name be blessed to all eternity\" is the nucleus of this Jewish mourner's prayer","response":"Kaddish","value":1600,"isDailyDouble":false},{"clue":"The U.S. Constitution was established to \"secure the blessings of\" this","response":"liberty","value":2000,"isDailyDouble":false}]},{"name":"WAY, WAY BACK IN THE DAY","clues":[{"clue":"Founded c. 800 B.C., this great city of antiquity on the north coast of Africa has a name meaning \"new town\\\"","response":"Carthage","value":400,"isDailyDouble":false},{"clue":"According to tradition, this ruler hid inside a rolled-up carpet to smuggle herself into Julius Caesar's quarters","response":"Cleopatra","value":800,"isDailyDouble":false},{"clue":"In the 490s B.C. he left the state of Lu along with his disciples after having been minister of crime","response":"Confucius","value":1200,"isDailyDouble":false},{"clue":"Britannica calls this Roman's \"Natural History\" an \"encyclopaedic scientific work of dubious accuracy\\\"","response":"Pliny (the Elder)","value":1600,"isDailyDouble":false},{"clue":"The ruler Ur-Nammu is credited with building the Great one of these pyramidal structures of Ur around 2100 B.C.","response":"a ziggurat","value":2000,"isDailyDouble":false}]},{"name":"BIRTH OF A NATION","clues":[{"clue":"The Republic of Ireland: April 18, 1949, this significant Monday","response":"Easter Monday","value":400,"isDailyDouble":false},{"clue":"The Czech Republic: January 1, 1993, with this author as its first president","response":"Václav Havel","value":800,"isDailyDouble":false},{"clue":"This country: September 21, 1991, with Levon Ter-Petrosyan as its first president","response":"Armenia","value":1200,"isDailyDouble":false},{"clue":"This country: June 17, 1944, with Sveinn Bjornsson as its first president","response":"Iceland","value":1600,"isDailyDouble":true},{"clue":"Indonesia: August 17, 1945, though this nation that had ruled it didn't recognize it until 1949","response":"the Netherlands","value":2000,"isDailyDouble":false}]},{"name":"THE QUOTABLE MOVIE","clues":[{"clue":"\\\"It can't be bargained with. It can't be reasoned with... & it absolutely will not stop, ever, until you are dead\\\"","response":"The Terminator","value":400,"isDailyDouble":false},{"clue":"From 2004: \"On Wednesdays we wear pink\\\"","response":"Mean Girls","value":800,"isDailyDouble":false},{"clue":"\\\"McLovin? What kind of a stupid name is that, Fogell?\\\"","response":"Superbad","value":1200,"isDailyDouble":false},{"clue":"From 2015: \"I don't do romance. My tastes are very singular. You wouldn't understand\\\"","response":"Fifty Shades of Grey","value":1600,"isDailyDouble":false},{"clue":"\\\"I drink your milkshake. I drink it up\\\"","response":"There Will Be Blood","value":2000,"isDailyDouble":false}]},{"name":"SHAKESPEARE","clues":[{"clue":"Bertolt Brecht's adaptation of this play is called \"Coriolan\\\"","response":"Coriolanus","value":400,"isDailyDouble":false},{"clue":"Peter Brook's unusual 1970 production of this play featured Oberon & Puck on trapezes","response":"A Midsummer Night's Dream","value":800,"isDailyDouble":false},{"clue":"\\\"The Merry Wives of Windsor\" is only about 10% this kind of verse","response":"blank verse (unrhymed iambic pentameter)","value":1200,"isDailyDouble":false},{"clue":"The plot of \"All's Well That Ends Well\" is derived from this Boccaccio work","response":"Decameron","value":1600,"isDailyDouble":false},{"clue":"Agamemnon's last line in this play is \"great Troy is ours, and our sharp wars are ended\\\"","response":"Troilus and Cressida","value":2000,"isDailyDouble":false}]},{"name":"TRANSPORTATION","clues":[{"clue":"In the early 1900s, the U.S. Weather Bureau flew the box type of these to lift weather instruments","response":"kite","value":400,"isDailyDouble":false},{"clue":"These chambers allow ships on a canal to move from one water level to another","response":"locks","value":800,"isDailyDouble":false},{"clue":"In the U.S. this runnerless sled is made of thin boards curved up in the front to form a prow","response":"toboggan","value":1200,"isDailyDouble":false},{"clue":"The first flight of an aircraft powered by this type of engine occurred in 1939 in Germany","response":"jet engine","value":1600,"isDailyDouble":false},{"clue":"In 1904 a rail loop around this Siberian lake was completed on the Trans-Siberian Railroad","response":"Lake Baikal","value":2000,"isDailyDouble":false}]},{"name":"BODY WORKS","clues":[{"clue":"Palpation is an exam of the body using the hands; insert 1 syllable & you get this pounding in the chest","response":"a palpitation","value":400,"isDailyDouble":false},{"clue":"It's the process of releasing an egg midway through a woman's cycle","response":"ovulation","value":800,"isDailyDouble":false},{"clue":"(Jimmy of the Clue Crew shows an anatomical animation on the monitor.) Of the spinal column's 24 movable vertebrae, half are located here, in the chest region, & are labeled T1 through T12, the \"T\" standing for this","response":"thoracic","value":1200,"isDailyDouble":false},{"clue":"Of the body's 2 chief kinds of glands, this type secretes hormones directly into the blood","response":"endocrine glands","value":1600,"isDailyDouble":false},{"clue":"(Jimmy of the Clue Crew demonstrates the clue in the lab.) Muscles that pull a body part away from the midline of the body, like the ones that allow me to move my legs apart, are said to be this type","response":"abductors","value":2000,"isDailyDouble":false}]},{"name":"THE ENVIRONMENT","clues":[{"clue":"Plans to expand Florida's Homestead Air Base may threaten the restoration of this national park","response":"Everglades","value":400,"isDailyDouble":false},{"clue":"By melting sea ice, global warming has reduced the number of the Adelie species of this bird","response":"penguin","value":800,"isDailyDouble":false},{"clue":"First released in Britain in 1876, the gray species of this arboreal rodent has overrun the native red","response":"squirrel","value":1200,"isDailyDouble":false},{"clue":"Court battles ended in 1996 in this country over Chisso Corp.'s 1950s dumping of mercury near Minamata","response":"Japan","value":1600,"isDailyDouble":false},{"clue":"In 1995 the French navy detained the Rainbow Warrior II to stop this group's protest of nuclear tests","response":"Greenpeace","value":2000,"isDailyDouble":true}]},{"name":"MUSIC","clues":[{"clue":"Term meaning \"in the church or chapel style\", it describes choral music that is sung unaccompanied","response":"a cappella","value":400,"isDailyDouble":false},{"clue":"Of the chorus, the verse, or the refrain, the one different from the other 2","response":"the verse","value":800,"isDailyDouble":false},{"clue":"Bartok & Copland wrote works specifically for this American clarinetist","response":"Benny Goodman","value":1200,"isDailyDouble":false},{"clue":"If there are no sharps or flats next to the treble clef, this is the key","response":"C","value":1600,"isDailyDouble":false},{"clue":"Collective title of the piano pieces Liszt based on Gypsy melodies","response":"Hungarian Rhapsodies","value":2000,"isDailyDouble":false}]},{"name":"SCIENCE","clues":[{"clue":"In physics a rad is the unit used to measure the amount of this absorbed by matter","response":"radiation","value":400,"isDailyDouble":false},{"clue":"In 1975 Isaac Asimov published a history of this scientific instrument called \"Eyes on the Universe\\\"","response":"the telescope","value":800,"isDailyDouble":false},{"clue":"It's the process by which light nuclei combine to form a single heavier nucleus","response":"fusion","value":1200,"isDailyDouble":false},{"clue":"Around 1820 Friedrich Mohs introduced the standard scale for measuring the hardness of these","response":"minerals","value":1600,"isDailyDouble":false},{"clue":"Now discredited, this theory held that living organisms originate from nonliving matter","response":"abiogenesis (or spontaneous generation)","value":2000,"isDailyDouble":false}]},{"name":"\\\"G\"EOGRAPHY","clues":[{"clue":"Jack & Jackie Kennedy lived in this section of D.C. before moving into the White House","response":"Georgetown","value":400,"isDailyDouble":false},{"clue":"The Japanese captured this island 3 days after the attack on Pearl Harbor","response":"Guam","value":800,"isDailyDouble":false},{"clue":"Martin Cruz Smith put this Moscow park on the map with his 1981 best seller of the same name","response":"Gorky Park","value":1200,"isDailyDouble":false},{"clue":"Belgian city that was the site of the signing of the treaty ending the War of 1812","response":"Ghent","value":1600,"isDailyDouble":false},{"clue":"Right next door to the Ivory Coast, it was called the Gold Coast for nearly 500 years","response":"Ghana","value":2000,"isDailyDouble":false}]},{"name":"POP EYE","clues":[{"clue":"To promote \"Everything Everywhere All at Once\", A24 Films sells pet these, complete with googly eyes & nest","response":"a pet rock","value":400,"isDailyDouble":false},{"clue":"A Dungeons & Dragons computer RPG from 1991 is called \"Eye of the\" this, also the name of a monster watching you there","response":"Eye of the Beholder","value":800,"isDailyDouble":false},{"clue":"On \"Orange Is the New Black\", Uzo Aduba played Suzanne Warren, who had this manic nickname","response":"Crazy Eyes","value":1200,"isDailyDouble":false},{"clue":"This band's 1980s cover of the Burt Bacharach & Hal David classic \"Always Something There To Remind Me\" was memorable","response":"Naked Eyes","value":1600,"isDailyDouble":false},{"clue":"Later a movie title, this collection of short stories was subtitled \"Five Secret Occasions in the Life of James Bond\\\"","response":"For Your Eyes Only","value":2000,"isDailyDouble":false}]},{"name":"QUOTES","clues":[{"clue":"D.H. Lawrence said, \"No absolute is going to make the lion lie down with\" this \"unless\" it's \"inside\\\"","response":"the lamb","value":400,"isDailyDouble":false},{"clue":"In the nursery rhyme, the lion & this animal were \"fighting for the crown\\\"","response":"the unicorn","value":800,"isDailyDouble":false},{"clue":"Song in which Elvis sang, \"I don't want to be your lion 'cause lions ain't the kind you love enough\\\"","response":"\\\"(Let Me Be Your) Teddy Bear\\\"","value":1200,"isDailyDouble":false},{"clue":"In \"Marmion\", Scott asked, \"And dar'st thou then to beard the lion\" here","response":"the den","value":1600,"isDailyDouble":false},{"clue":"In Judges 14:15, he \"came to the vineyards of Timnath: and, behold, a young lion roared against him\\\"","response":"Samson","value":2000,"isDailyDouble":false}]},{"name":"LIGHT VERSE","clues":[{"clue":"This epic poem by John Milton calls angels \"progeny of light\\\"","response":"Paradise Lost","value":400,"isDailyDouble":false},{"clue":"\\\"Hand in hand, on the edge of the sand,\" these 2 title animals of an Edward Lear poem \"danced by the light of the moon\\\"","response":"the Owl and the Pussycat","value":800,"isDailyDouble":false},{"clue":"One of her sonnets says, \"I love thee to the level of everyday's most quiet need, by sun and candle-light\\\"","response":"Elizabeth Barrett Browning","value":1200,"isDailyDouble":false},{"clue":"This poem by Dylan Thomas says, \"old age should burn and rave at close of day; rage, rage against the dying of the light\\\"","response":"\\\"Do Not Go Gentle into that Good Night\\\"","value":1600,"isDailyDouble":false},{"clue":"\\\"Like a poet hidden in the light of thought, singing hymns unbidden\", said Shelley in his ode to this bird","response":"a skylark","value":2000,"isDailyDouble":false}]},{"name":"DOCTOR TALK","clues":[{"clue":"(Jimmy of the Clue Crew at the office of Dr. Jill Broffman.) \"Tachycardic\" that means this is speeded up","response":"heart rate","value":400,"isDailyDouble":false},{"clue":"(Cheryl of the Clue Crew at the Dr.'s office.) \"Cranialgia\" I have one of these, also a synonym for any annoyance","response":"headache","value":800,"isDailyDouble":false},{"clue":"(Sarah of the Clue Crew at the Dr.'s office.) \"Cerumen\" I can't hear you-I have too much of this","response":"earwax","value":1200,"isDailyDouble":false},{"clue":"(Sofia of the Clue Crew at the Dr.'s office.) \"Varicella\" that's just this childhood disease","response":"chickenpox","value":1600,"isDailyDouble":false},{"clue":"(Jimmy of the Clue Crew at the Dr.'s office.) \"Rhinitis\" you mean I have inflammation in this body part","response":"nose","value":2000,"isDailyDouble":false}]},{"name":"LITERARY TRANSLATIONS","clues":[{"clue":"Many of these English Christmas songs are translations, like \"Silent Night\" from German","response":"Carols","value":400,"isDailyDouble":false},{"clue":"Gilbert Adair faithfully adapted Georges Perec's novel \"A Void\", written without this vowel","response":"E","value":800,"isDailyDouble":false},{"clue":"Translator Rosemary Edmonds leaves the final \"A\" off the last name of this Tolstoy title heroine","response":"Anna Karenina","value":1200,"isDailyDouble":false},{"clue":"2 translators of this man's \"The Satanic Verses\" were brutally attacked in July 1991","response":"Salman Rushdie","value":1600,"isDailyDouble":false},{"clue":"Rabindranath Tagore translated his own poetry into English from this language spoken in Dhaka","response":"Bengali","value":2000,"isDailyDouble":false}]}]